Workbook

Sheet Jan - Formula
A1: {=[1]Jan!$A$1:$P$3103} -> job_title_short | B1: job_title | C1: job_location | D1: job_via | E1: job_schedule_type | F1: job_work_from_home | G1: search_location | H1: job_posted_date | I1: job_no_degree_mention | J1: job_health_insurance | K1: job_country | L1: salary_rate | M1: salary_year_avg | N1: salary_hour_avg | O1: company_name | P1: job_skills
A2: Data Scientist | B2: Data Scientist - TikTok Ads | C2: Mountain View, CA | D2: via LinkedIn | E2: Full-time | F2: FALSE | G2: California, United States | H2: 44928.626 | I2: FALSE | J2: TRUE | K2: United States | L2: year | M2: 224500 | N2: 0 | O2: TikTok | P2: ['r', 'python', 'matlab', 'sql']
A3: Data Scientist | B3: Data Scientist - Technical Platform | C3: Mountain View, CA | D3: via LinkedIn | E3: Full-time | F3: FALSE | G3: California, United States | H3: 44938.17 | I3: FALSE | J3: TRUE | K3: United States | L3: year | M3: 157500 | N3: 0 | O3: TikTok | P3: ['sql', 'python']
A4: Data Scientist | B4: Data Scientist - Computer Vision | C4: Paris, France | D4: via Ai-Jobs.net | E4: Full-time | F4: FALSE | G4: France | H4: 44956.343 | I4: FALSE | J4: FALSE | K4: France | L4: year | M4: 88128 | N4: 0 | O4: digiRocks | P4: ['python', 'c++', 'pytorch', 'tensorflow', 'keras']
A5: Data Scientist | B5: Senior Actuarial Consultant and Data Scientist - Remote | C5: Las Vegas, NV | D5: via Las Vegas, NV - Geebo | E5: Full-time | F5: FALSE | G5: California, United States | H5: 44953.004 | I5: FALSE | J5: TRUE | K5: United States | L5: hour | M5: 0 | N5: 24 | O5: UnitedHealth Group | P5: ['r', 'python', 'vba', 'sas', 'sas', 'sql', 'databricks', 'excel']
A6: Data Scientist | B6: Data Scientist Digital Effectiveness Operations & Technology Analytics | C6: Sun City, AZ | D6: via ZipRecruiter | E6: Full-time | F6: FALSE | G6: California, United States | H6: 44955.42 | I6: FALSE | J6: TRUE | K6: United States | L6: year | M6: 105800 | N6: 0 | O6: Cox Communications | P6: ['sql', 'python', 'aws', 'pandas', 'numpy', 'scikit-learn', 'pyspark', 'tableau']
A7: Data Scientist | B7: Data Scientist - Marketing Analytics | C7: Irving, TX | D7: via LinkedIn | E7: Full-time | F7: FALSE | G7: Texas, United States | H7: 44950.668 | I7: FALSE | J7: TRUE | K7: United States | L7: year | M7: 115000 | N7: 0 | O7: Cottonwood Financial | P7: ['sql', 'sas', 'sas', 'python', 'r']
A8: Senior Data Analyst | B8: Senior Data Analyst Business Optimization Intelligence | C8: Bailey's Crossroads, VA | D8: via ZipRecruiter | E8: Full-time | F8: FALSE | G8: New York, United States | H8: 44930.417 | I8: FALSE | J8: TRUE | K8: United States | L8: year | M8: 96500 | N8: 0 | O8: Cox Communications | P8: ['sql', 'snowflake', 'aws', 'microstrategy', 'tableau', 'excel']
A9: Data Engineer | B9: IT & Strategy Talent Programme - AI/ML and Data Engineer | C9: Hamburg, Germany | D9: via Ai-Jobs.net | E9: Full-time | F9: FALSE | G9: Germany | H9: 44938.864 | I9: FALSE | J9: FALSE | K9: Germany | L9: year | M9: 98301.5 | N9: 0 | O9: Vattenfall | P9: ['azure']
A10: Senior Data Scientist | B10: Senior Data Scientist | C10: El Mirage, AZ | D10: via ZipRecruiter | E10: Full-time | F10: FALSE | G10: California, United States | H10: 44955.42 | I10: FALSE | J10: TRUE | K10: United States | L10: year | M10: 116700 | N10: 0 | O10: Cox Communications | P10: ['sql', 'r', 'python', 'scala', 'java', 'c++', 'sas', 'sas', 'aws', 'spark', 'ggplot2', 'pandas', 'numpy', 'scikit-learn', 'tableau']
A11: Data Engineer | B11: Data Engineer | C11: Chicago, IL | D11: via Indeed | E11: Full-time | F11: FALSE | G11: California, United States | H11: 44939.798 | I11: FALSE | J11: TRUE | K11: United States | L11: year | M11: 102500 | N11: 0 | O11: Alliant Credit Union | P11: ['sql', 'azure', 'tableau']
A12: Senior Data Scientist | B12: Senior Data Scientist | C12: Austin, TX | D12: via Indeed | E12: Full-time | F12: FALSE | G12: Texas, United States | H12: 44930.92 | I12: FALSE | J12: TRUE | K12: United States | L12: year | M12: 145000 | N12: 0 | O12: CyberCoders | P12: ['python', 'azure', 'pytorch', 'tensorflow', 'opencv', 'datarobot']
A13: Data Engineer | B13: Systems & Data Engineer | C13: Boston, MA | D13: via LinkedIn | E13: Full-time | F13: FALSE | G13: Illinois, United States | H13: 44952.675 | I13: FALSE | J13: TRUE | K13: United States | L13: year | M13: 75000 | N13: 0 | O13: New England Board of Higher Education | P13: ['sql', 'python', 'r', 'java', 'scala', 'aws', 'azure', 'tableau']
... A17: Data Scientist | B17: Data Scientist I | C17: Boston, MA | D17: via ZipRecruiter | E17: Full-time | F17: FALSE | G17: New York, United States | H17: 44931.669 | I17: FALSE | J17: FALSE | K17: United States | L17: year | M17: 57500 | N17: 0 | O17: Tresume and Asta CRS | P17: ['r', 'sql', 'python', 'scala', 'java', 'c++']
A18: Data Analyst | B18: Lead-Data Analyst | C18: St James, MO | D18: via My ArkLaMiss Jobs | E18: Full-time | F18: FALSE | G18: Illinois, United States | H18: 44928.751 | I18: FALSE | J18: TRUE | K18: United States | L18: year | M18: 144481.5 | N18: 0 | O18: EDWARD JONES | P18: 0
A19: Data Scientist | B19: Data Science Instructor | C19: San Antonio, TX | D19: via LinkedIn | E19: Full-time | F19: FALSE | G19: Sudan | H19: 44936.752 | I19: FALSE | J19: TRUE | K19: Sudan | L19: year | M19: 77500 | N19: 0 | O19: Codeup | P19: ['python', 'sql', 'matplotlib', 'seaborn', 'spark', 'hadoop', 'jupyter', 'tableau']
A20: Data Engineer | B20: Big Data Engineer | C20: Chicago, IL | D20: via LinkedIn | E20: Full-time | F20: FALSE | G20: Sudan | H20: 44952.328 | I20: FALSE | J20: FALSE | K20: Sudan | L20: year | M20: 105000 | N20: 0 | O20: Robert Half | P20: ['python', 'sql', 'go', 'aws', 'databricks', 'spark', 'pyspark', 'airflow', 'alteryx', 'tableau']
A21: Data Analyst | B21: Institutional Credit Management - Lending Data Analyst - Vice... | C21: Pinellas Park, FL | D21: via ComputerWork | E21: Full-time | F21: FALSE | G21: Florida, United States | H21: 44951.669 | I21: FALSE | J21: FALSE | K21: United States | L21: year | M21: 132315 | N21: 0 | O21: Citi | P21: ['cognos', 'tableau']
A22: Senior Data Scientist | B22: AI/ML - Senior Data Science Manager, AI/ML Data | C22: Cupertino, CA | D22: via My Champlain Valley Jobs | E22: Full-time | F22: FALSE | G22: California, United States | H22: 44938.754 | I22: FALSE | J22: TRUE | K22: United States | L22: year | M22: 173000 | N22: 0 | O22: Apple | P22: 0
A23: Data Analyst | B23: Experian Data Analyst Remote / Telecommute Jobs | C23: Anywhere | D23: via Clearance Jobs | E23: Full-time | F23: TRUE | G23: New York, United States | H23: 44929.894 | I23: FALSE | J23: FALSE | K23: United States | L23: year | M23: 112500 | N23: 0 | O23: Seneca Resources, LLC | P23: ['aws', 'linux']
A24: Data Scientist | B24: Electronics Data Scientist Intern | C24: Anywhere | D24: via Indeed | E24: Full-time | F24: TRUE | G24: California, United States | H24: 44953.379 | I24: FALSE | J24: FALSE | K24: United States | L24: hour | M24: 0 | N24: 21.75 | O24: MilliporeSigma | P24: ['excel', 'outlook']
A25: Data Scientist | B25: Data Scientist (Genomics/Genetics, Python, AWS) - no c2c | C25: Anywhere | D25: via LinkedIn | E25: Contractor | F25: TRUE | G25: Texas, United States | H25: 44935.753 | I25: FALSE | J25: FALSE | K25: United States | L25: hour | M25: 0 | N25: 66.5 | O25: neteffects | P25: ['python', 'r', 'sql', 'java', 'aws', 'gcp', 'airflow', 'docker', 'git', 'kubernetes']
A26: Senior Data Analyst | B26: Senior Data Analyst | C26: Ontario, CA | D26: via Indeed | E26: Full-time | F26: FALSE | G26: California, United States | H26: 44937.418 | I26: FALSE | J26: TRUE | K26: United States | L26: hour | M26: 0 | N26: 34.875 | O26: Prime Healthcare Management Inc | P26: ['sql', 'excel']
A27: Data Analyst | B27: Data Analyst (Remote) | C27: Anywhere | D27: via Indeed | E27: Full-time | F27: TRUE | G27: Georgia | H27: 44940.405 | I27: FALSE | J27: FALSE | K27: United States | L27: year | M27: 52500 | N27: 0 | O27: Acosta, Inc. | P27: ['windows', 'excel', 'word', 'powerpoint', 'power bi']
A28: Data Engineer | B28: Sr. Data Engineer | C28: Austin, TX | D28: via Indeed | E28: Full-time | F28: FALSE | G28: Georgia | H28: 44947.598 | I28: TRUE | J28: FALSE | K28: United States | L28: year | M28: 164500 | N28: 0 | O28: Charles Schwab | P28: ['sql', 'python', 'java', 'gcp', 'bigquery', 'aws', 'vmware', 'pandas', 'spark', 'airflow', 'kafka', 'splunk', 'tableau', 'jira', 'confluence']
A29: Data Engineer | B29: Scientific Data Engineer (Remote Friendly) | C29: Anywhere | D29: via LinkedIn | E29: Full-time | F29: TRUE | G29: Texas, United States | H29: 44951.975 | I29: FALSE | J29: FALSE | K29: United States | L29: year | M29: 149874 | N29: 0 | O29: Berkeley Lab | P29: ['python', 'java', 'javascript', 'bash', 'nosql', 'mysql', 'oracle', 'aws', 'linux']
A30: Data Analyst | B30: Lead Business Data Analyst - Global Delivery Services | C30: Santa Fe, NM | D30: via DirectlyApply | E30: Full-time | F30: FALSE | G30: Sudan | H30: 44932.163 | I30: TRUE | J30: FALSE | K30: Sudan | L30: year | M30: 115775 | N30: 0 | O30: UKG (Ultimate Kronos Group) | P30: ['power bi', 'excel', 'tableau']
A31: Senior Data Analyst | B31: Senior Data Analyst - Cox Communities | C31: Oakton, VA | D31: via ZipRecruiter | E31: Full-time | F31: FALSE | G31: New York, United States | H31: 44930.417 | I31: FALSE | J31: TRUE | K31: United States | L31: year | M31: 96500 | N31: 0 | O31: Cox Communications | P31: ['sql', 'alteryx', 'tableau']
A32: Senior Data Scientist | B32: Senior Data Scientist , Health Equity – Chicago, Boston, OR Remote | C32: Anywhere | D32: via Indeed | E32: Full-time | F32: TRUE | G32: Illinois, United States | H32: 44942.905 | I32: FALSE | J32: TRUE | K32: United States | L32: year | M32: 135000 | N32: 0 | O32: CVS Health | P32: ['python', 'sql', 'gcp', 'azure', 'aws', 'hadoop']
A33: Data Scientist | B33: Manufacturing Data Scientist | C33: Englewood, CO | D33: via Indeed | E33: Full-time | F33: FALSE | G33: Sudan | H33: 44939.891 | I33: FALSE | J33: FALSE | K33: Sudan | L33: year | M33: 110000 | N33: 0 | O33: Scytec Consulting Inc. | P33: ['sql', 'nosql', 'mongodb', 'mongodb', 'c#', 'sql server', 'azure', 'aws', 'git']
A34: Data Engineer | B34: Data Engineer | C34: New York, NY | D34: via LinkedIn | E34: Full-time | F34: FALSE | G34: Texas, United States | H34: 44950.632 | I34: FALSE | J34: FALSE | K34: United States | L34: year | M34: 155000 | N34: 0 | O34: Revel IT | P34: ['sql', 'nosql', 'python', 'ruby', 'ruby', 'mysql', 'redshift', 'aws', 'tableau']
A35: Data Scientist | B35: Mathematics Statistician or Statistician (Data Scientist) 12 Month... | C35: Buffalo, NY | D35: via Buffalo, NY - Geebo | E35: Full-time | F35: FALSE | G35: Illinois, United States | H35: 44942.003 | I35: FALSE | J35: TRUE | K35: United States | L35: hour | M35: 0 | N35: 24 | O35: Internal Revenue Service | P35: ['c', 'r', 'python', 'sql', 'java', 'oracle']
A36: Data Analyst | B36: Data Analyst | C36: 0 | D36: via LinkedIn | E36: Full-time | F36: FALSE | G36: New York, United States | H36: 44929.686 | I36: TRUE | J36: FALSE | K36: United States | L36: year | M36: 97500 | N36: 0 | O36: Robert Half | P36: ['sql', 't-sql', 'sql server', 'azure', 'ssrs', 'ssis']
A37: Data Engineer | B37: Data Engineer | C37: Washington, DC | D37: via PHL17 Jobs | E37: Full-time | F37: FALSE | G37: Georgia | H37: 44941.583 | I37: FALSE | J37: FALSE | K37: United States | L37: year | M37: 145000 | N37: 0 | O37: Peraton | P37: ['python', 'sql', 'neo4j', 'mysql', 'aws', 'spark', 'express', 'splunk', 'git', 'jira', 'confluence']
A38: Data Engineer | B38: Data Engineer - A4370 | C38: Pleasanton, CA | D38: via Ai-Jobs.net | E38: Full-time | F38: FALSE | G38: California, United States | H38: 44937.839 | I38: FALSE | J38: TRUE | K38: United States | L38: year | M38: 147500 | N38: 0 | O38: Nisum | P38: ['sql', 'spark']
A39: Senior Data Engineer | B39: Senior Data Engineer | C39: Woonsocket, RI | D39: via Indeed | E39: Full-time | F39: FALSE | G39: Illinois, United States | H39: 44933.921 | I39: FALSE | J39: TRUE | K39: United States | L39: year | M39: 135000 | N39: 0 | O39: CVS Health | P39: ['sql', 'python', 'bash', 'oracle', 'snowflake', 'azure', 'gcp', 'hadoop']
A40: Senior Data Analyst | B40: Senior Data Analyst, Business Optimization | C40: Smyrna, GA | D40: via ZipRecruiter | E40: Full-time | F40: FALSE | G40: Georgia | H40: 44953.436 | I40: FALSE | J40: TRUE | K40: United States | L40: year | M40: 96500 | N40: 0 | O40: Cox Communications | P40: ['swift', 'sql', 'excel', 'powerpoint', 'microstrategy', 'tableau']
A41: Data Engineer | B41: Data Engineer | C41: Malvern, PA | D41: via Dice | E41: Full-time | F41: FALSE | G41: Georgia | H41: 44935.863 | I41: TRUE | J41: FALSE | K41: United States | L41: year | M41: 70000 | N41: 0 | O41: Acadia Technologies, Inc. | P41: ['pyspark']
A42: Senior Data Scientist | B42: Senior Data Scientist - ProServe | C42: Lakeland, FL | D42: via Lakeland, FL - Geebo | E42: Full-time | F42: FALSE | G42: Florida, United States | H42: 44929.983 | I42: FALSE | J42: FALSE | K42: United States | L42: hour | M42: 0 | N42: 24 | O42: Amazon Web Services, Inc. | P42: ['aws', 'mxnet', 'tensorflow', 'pytorch', 'scikit-learn']
A43: Senior Data Analyst | B43: Senior Data Analyst | C43: New York, NY | D43: via LinkedIn | E43: Full-time | F43: FALSE | G43: New York, United States | H43: 44930.061 | I43: FALSE | J43: TRUE | K43: United States | L43: year | M43: 170000 | N43: 0 | O43: Harnham | P43: ['sql', 'python', 'r', 'tableau', 'power bi', 'looker']
A44: Machine Learning Engineer | B44: Senior Machine Learning Engineer / Python Developer | C44: Lviv, Lviv Oblast, Ukraine | D44: via Ai-Jobs.net | E44: Full-time | F44: FALSE | G44: Ukraine | H44: 44945.193 | I44: FALSE | J44: FALSE | K44: Ukraine | L44: year | M44: 104668 | N44: 0 | O44: LoopMe | P44: ['python', 'r', 'elasticsearch', 'airflow', 'spark', 'kafka']
A45: Data Engineer | B45: Cloud Data Engineer | C45: Broomfield, CO | D45: via LinkedIn | E45: Full-time | F45: FALSE | G45: Sudan | H45: 44951.916 | I45: FALSE | J45: TRUE | K45: Sudan | L45: year | M45: 125000 | N45: 0 | O45: Noodles & Company | P45: ['python', 'sql', 'bigquery', 'gcp', 'power bi', 'git']
A46: Data Scientist | B46: Engineering Data Scientist, Ad Ranking | C46: New York, NY | D46: via Ladders | E46: Full-time | F46: FALSE | G46: New York, United States | H46: 44941.252 | I46: FALSE | J46: TRUE | K46: United States | L46: year | M46: 350000 | N46: 0 | O46: Snap Inc | P46: ['sql', 'python', 'r', 'express']
A47: Machine Learning Engineer | B47: Senior AI Research Scientist | C47: Lisbon, Portugal | D47: via Ai-Jobs.net | E47: Full-time | F47: FALSE | G47: Portugal | H47: 44935.885 | I47: FALSE | J47: FALSE | K47: Portugal | L47: year | M47: 94342.5 | N47: 0 | O47: Unbabel | P47: ['python', 'c++', 'pytorch', 'tensorflow']
A48: Data Engineer | B48: Lead Business Intelligence / Data Engineer: | C48: Brentwood, TN | D48: via LinkedIn | E48: Full-time | F48: FALSE | G48: Illinois, United States | H48: 44932.798 | I48: FALSE | J48: FALSE | K48: United States | L48: year | M48: 127500 | N48: 0 | O48: Robert Half | P48: ['python', 'r', 't-sql', 'sql', 'go', 'oracle', 'jupyter', 'jquery', 'sharepoint', 'jenkins', 'docker', 'confluence']
... A66: Data Engineer | B66: ERP Data Engineer | C66: Lansing, MI | D66: via LinkedIn | E66: Full-time | F66: FALSE | G66: Sudan | H66: 44936.71 | I66: FALSE | J66: FALSE | K66: Sudan | L66: year | M66: 80000 | N66: 0 | O66: Venteon | P66: ['sql', 'sap']
A67: Data Scientist | B67: Head of Data Science | C67: Anywhere | D67: via LinkedIn | E67: Full-time | F67: TRUE | G67: Sudan | H67: 44930.581 | I67: FALSE | J67: TRUE | K67: Sudan | L67: year | M67: 215000 | N67: 0 | O67: Lawrence Harvey | P67: 0
A68: Senior Data Analyst | B68: Sr Data Analyst | $90k | Lake Forest, IL | C68: Lake Forest, IL | D68: via Recruit.net | E68: Full-time | F68: FALSE | G68: Illinois, United States | H68: 44949.002 | I68: TRUE | J68: FALSE | K68: United States | L68: year | M68: 90000 | N68: 0 | O68: Trinity Intl. | P68: 0
A69: Data Analyst | B69: SQL Developer/Data Analyst | C69: New York, NY | D69: via Dice | E69: Contractor | F69: FALSE | G69: New York, United States | H69: 44956.542 | I69: FALSE | J69: FALSE | K69: United States | L69: hour | M69: 0 | N69: 60 | O69: Infosight Consulting Inc | P69: ['sql', 'python', 'sql server', 'oracle']
A70: Data Scientist | B70: Data Analyst / Data Scientist | C70: Anywhere | D70: via Y Combinator | E70: Full-time | F70: TRUE | G70: California, United States | H70: 44946.723 | I70: FALSE | J70: TRUE | K70: United States | L70: year | M70: 160000 | N70: 0 | O70: Y Combinator | P70: ['sql', 'python']
A71: Data Analyst | B71: Data Analyst with FinTech- | C71: Austin, TX | D71: via Austin, TX - Geebo | E71: Full-time | F71: FALSE | G71: Texas, United States | H71: 44942.001 | I71: TRUE | J71: FALSE | K71: United States | L71: hour | M71: 0 | N71: 24 | O71: EXPERIS | P71: ['sql', 'snowflake']
A72: Senior Data Scientist | B72: Senior Data Scientist | C72: Austin, TX | D72: via LinkedIn | E72: Full-time | F72: FALSE | G72: Texas, United States | H72: 44937.962 | I72: FALSE | J72: TRUE | K72: United States | L72: year | M72: 160000 | N72: 0 | O72: Primis | P72: ['python', 'sql', 'tableau']
A73: Senior Data Engineer | B73: Senior IT Data Engineer | C73: Fort Meade, MD | D73: via Ladders | E73: Full-time | F73: FALSE | G73: Georgia | H73: 44948.418 | I73: FALSE | J73: TRUE | K73: United States | L73: year | M73: 150000 | N73: 0 | O73: Leidos | P73: ['python', 'java', 'kafka', 'linux', 'ansible', 'flow']
A74: Senior Data Engineer | B74: Senior Data Engineer | C74: San Diego, CA | D74: via LinkedIn | E74: Full-time | F74: FALSE | G74: Illinois, United States | H74: 44932.715 | I74: FALSE | J74: TRUE | K74: United States | L74: year | M74: 140000 | N74: 0 | O74: Robert Half | P74: ['python', 'sql', 'nosql', 'azure', 'oracle', 'databricks', 'phoenix']
A75: Data Engineer | B75: Data Engineer | C75: Anywhere | D75: via Robert Half | E75: Full-time | F75: TRUE | G75: New York, United States | H75: 44935.588 | I75: TRUE | J75: FALSE | K75: United States | L75: year | M75: 140000 | N75: 0 | O75: Robert Half | P75: ['python', 'sql', 'java', 't-sql', 'oracle', 'spark', 'pyspark', 'kafka', 'airflow', 'linux', 'sap', 'github']
A76: Senior Data Scientist | B76: Senior Data Scientist | C76: Foster City, CA | D76: via Ai-Jobs.net | E76: Full-time | F76: FALSE | G76: California, United States | H76: 44932.253 | I76: FALSE | J76: TRUE | K76: United States | L76: year | M76: 161000 | N76: 0 | O76: Visa | P76: ['python', 'r', 'sql', 'spark', 'jupyter', 'word', 'excel', 'powerpoint']
A77: Data Engineer | B77: Data Engineer | C77: Anywhere | D77: via Indeed | E77: Full-time | F77: TRUE | G77: California, United States | H77: 44957.671 | I77: FALSE | J77: FALSE | K77: United States | L77: year | M77: 85000 | N77: 0 | O77: DBSI Services | P77: ['sql', 'visual basic', 'oracle']
A78: Data Analyst | B78: Data Analyst | C78: McLean, VA | D78: via LinkedIn | E78: Contractor | F78: FALSE | G78: New York, United States | H78: 44937.667 | I78: TRUE | J78: FALSE | K78: United States | L78: hour | M78: 0 | N78: 40 | O78: Mindlance | P78: ['python', 'sql', 'postgresql', 'aws', 'tableau']
A79: Data Engineer | B79: Data Engineer | C79: Anywhere | D79: via LinkedIn | E79: Full-time | F79: TRUE | G79: Canada | H79: 44950.01 | I79: FALSE | J79: FALSE | K79: Canada | L79: year | M79: 124000 | N79: 0 | O79: GRIN | P79: ['python', 'sql', 'no-sql', 'bigquery', 'snowflake', 'airflow', 'kafka', 'spark']
A80: Data Scientist | B80: Mathematical Statistician (Data Scientist) or Statistician (Data... | C80: Charlotte, NC | D80: via DiversityJobs | E80: Full-time | F80: FALSE | G80: Illinois, United States | H80: 44937.379 | I80: FALSE | J80: TRUE | K80: United States | L80: year | M80: 143910.5 | N80: 0 | O80: Internal Revenue Service | P80: ['c']
... A140: Data Engineer | B140: Senior Consultant - Data Engineer | C140: Kuala Lumpur, Federal Territory of Kuala Lumpur, Malaysia | D140: via Ai-Jobs.net | E140: Full-time | F140: FALSE | G140: Malaysia | H140: 44936.402 | I140: FALSE | J140: FALSE | K140: Malaysia | L140: year | M140: 147500 | N140: 0 | O140: Capco | P140: ['sql', 'azure', 'databricks', 'power bi', 'tableau']
A141: Senior Data Scientist | B141: Senior Data Scientist | C141: Anywhere | D141: via LinkedIn | E141: Full-time | F141: TRUE | G141: Sudan | H141: 44939.599 | I141: FALSE | J141: TRUE | K141: Sudan | L141: year | M141: 200000 | N141: 0 | O141: Storm3 | P141: 0
A142: Senior Data Engineer | B142: Senior Data Engineer & Innovation - FULL-TIME role - Need US... | C142: Anywhere | D142: via LinkedIn | E142: Full-time | F142: TRUE | G142: Illinois, United States | H142: 44945.826 | I142: FALSE | J142: FALSE | K142: United States | L142: year | M142: 95000 | N142: 0 | O142: SREYO | P142: ['sql', 'python', 'snowflake', 'redshift', 'aws', 'hadoop', 'numpy', 'pandas', 'pyspark']
A143: Data Engineer | B143: Data Engineer | C143: United States | D143: via LinkedIn | E143: Full-time | F143: FALSE | G143: Georgia | H143: 44935.321 | I143: FALSE | J143: FALSE | K143: United States | L143: year | M143: 127500 | N143: 0 | O143: JBAndrews | P143: ['python', 'sql', 'aws', 'redshift']
A144: Senior Data Analyst | B144: ICM CCR Senior Data Analyst, AVP | C144: Bay Harbor Islands, FL | D144: via My ArkLaMiss Jobs | E144: Full-time | F144: FALSE | G144: Florida, United States | H144: 44942.763 | I144: FALSE | J144: FALSE | K144: United States | L144: year | M144: 146500 | N144: 0 | O144: Citi | P144: ['python', 'r', 'sql', 'vba', 'tableau', 'power bi', 'excel']
A145: Data Engineer | B145: Data Engineer 1 | C145: Chicago, IL | D145: via Ladders | E145: Full-time | F145: FALSE | G145: Illinois, United States | H145: 44950.299 | I145: FALSE | J145: TRUE | K145: United States | L145: year | M145: 90000 | N145: 0 | O145: Jones Lang LaSalle Incorporated | P145: ['python', 'scala', 'java', 'sql', 'databricks', 'spark', 'flow']
A146: Data Scientist | B146: Lead Data Scientist | C146: Miami, FL | D146: via Ladders | E146: Full-time | F146: FALSE | G146: Florida, United States | H146: 44944.38 | I146: FALSE | J146: TRUE | K146: United States | L146: year | M146: 175000 | N146: 0 | O146: Chief | P146: ['python', 'sql', 'aws', 'redshift']
A147: Data Scientist | B147: Data Scientist - Biotech | C147: Pittsburgh, PA | D147: via LinkedIn | E147: Full-time | F147: FALSE | G147: Georgia | H147: 44949.434 | I147: FALSE | J147: FALSE | K147: United States | L147: year | M147: 130000 | N147: 0 | O147: CyberCoders | P147: ['python', 'r', 'aws', 'pytorch', 'tensorflow', 'keras', 'word', 'git']
A148: Data Engineer | B148: Data Engineer | C148: Waltham, MA | D148: via ZipRecruiter | E148: Full-time | F148: FALSE | G148: New York, United States | H148: 44946.477 | I148: TRUE | J148: FALSE | K148: United States | L148: year | M148: 96500 | N148: 0 | O148: National Grid (UK) | P148: ['oracle']
A149: Data Scientist | B149: Sr Data Scientist | C149: Charlotte, NC | D149: via Dice | E149: Full-time | F149: FALSE | G149: Florida, United States | H149: 44946.852 | I149: FALSE | J149: FALSE | K149: United States | L149: hour | M149: 0 | N149: 65 | O149: Teksoft Systems Inc | P149: ['go', 'python', 'r', 'aws', 'sharepoint', 'word']
A150: Data Engineer | B150: Data Engineer (Remote) | C150: Anywhere | D150: via ZipRecruiter | E150: Full-time | F150: TRUE | G150: Sudan | H150: 44957.13 | I150: FALSE | J150: TRUE | K150: Sudan | L150: year | M150: 112500 | N150: 0 | O150: Seerist, Inc | P150: ['python', 'javascript', 'elasticsearch', 'aws', 'node.js']
A151: Data Engineer | B151: Data Engineer | C151: Brussels, Belgium | D151: via Ai-Jobs.net | E151: Full-time | F151: FALSE | G151: Belgium | H151: 44933.262 | I151: FALSE | J151: FALSE | K151: Belgium | L151: year | M151: 98301.5 | N151: 0 | O151: Talan | P151: ['sql', 'python', 'snowflake', 'redshift']
A152: Data Scientist | B152: Data Scientist | C152: Anywhere | D152: via Indeed | E152: Full-time | F152: TRUE | G152: California, United States | H152: 44953.962 | I152: FALSE | J152: TRUE | K152: United States | L152: hour | M152: 0 | N152: 67.605003 | O152: Intermountain Healthcare | P152: ['python', 'r', 'sql', 'scala', 'nosql', 'gcp', 'azure', 'spark', 'hadoop']
A153: Data Scientist | B153: Python Data Scientist for API | C153: Anywhere | D153: via Upwork | E153: Contractor | F153: TRUE | G153: Illinois, United States | H153: 44957.129 | I153: FALSE | J153: FALSE | K153: United States | L153: hour | M153: 0 | N153: 100 | O153: Upwork | P153: ['python', 'flask', 'fastapi']
... A155: Data Engineer | B155: Lead Data Engineer (Remote) | C155: Beaverton, OR | D155: via Ladders | E155: Full-time | F155: FALSE | G155: New York, United States | H155: 44928.462 | I155: FALSE | J155: FALSE | K155: United States | L155: year | M155: 150000 | N155: 0 | O155: NIKE, Inc | P155: ['nosql', 'sql', 'python', 'scala', 'java', 'aws', 'hadoop', 'spark', 'kafka', 'github', 'confluence']
A156: Data Engineer | B156: Lead Data Engineer | C156: Tennessee | D156: via LinkedIn | E156: Full-time | F156: FALSE | G156: Sudan | H156: 44951.541 | I156: FALSE | J156: FALSE | K156: Sudan | L156: year | M156: 125000 | N156: 0 | O156: MFM Search LLC | P156: 0
A157: Senior Data Scientist | B157: Senior Data Scientist | C157: Reston, VA | D157: via Ladders | E157: Full-time | F157: FALSE | G157: Georgia | H157: 44938.514 | I157: FALSE | J157: TRUE | K157: United States | L157: year | M157: 375000 | N157: 0 | O157: Noblis | P157: ['python', 'scala', 'r', 'java', 'neo4j', 'aws', 'hadoop', 'spark', 'splunk']
A158: Data Engineer | B158: Data Engineer | C158: Phoenix, AZ | D158: via Ladders | E158: Full-time | F158: FALSE | G158: Georgia | H158: 44928.304 | I158: FALSE | J158: TRUE | K158: United States | L158: year | M158: 125000 | N158: 0 | O158: Deckers Brands | P158: ['python', 'sql', 'aws', 'spark', 'linux', 'git', 'github', 'docker']
A159: Data Engineer | B159: Data Engineer, Smart Factory Solutions | C159: Troy, AL | D159: via Ladders | E159: Full-time | F159: FALSE | G159: California, United States | H159: 44954.505 | I159: FALSE | J159: FALSE | K159: United States | L159: year | M159: 90000 | N159: 0 | O159: Magna | P159: ['sql', 'nosql', 'sql server', 'mysql', 'oracle', 'gdpr', 'excel', 'word', 'powerpoint', 'unity']
A160: Senior Data Scientist | B160: Senior Director Data Science & ML | C160: Anywhere | D160: via LinkedIn | E160: Full-time | F160: TRUE | G160: Illinois, United States | H160: 44952.755 | I160: FALSE | J160: FALSE | K160: United States | L160: year | M160: 315000 | N160: 0 | O160: Life Science People | P160: 0
A161: Data Engineer | B161: Mid-level /Senior / Lead Data Engineer | C161: Cherry Hill, NJ | D161: via Ladders | E161: Full-time | F161: FALSE | G161: Texas, United States | H161: 44937.267 | I161: FALSE | J161: FALSE | K161: United States | L161: year | M161: 125000 | N161: 0 | O161: Lorven technologies | P161: ['python', 'shell', 'oracle', 'azure', 'aws', 'unix']
A162: Data Analyst | B162: Public Health Data Analyst - REMOTE | C162: Atlanta, GA | D162: via Atlanta, GA - Geebo | E162: Full-time | F162: FALSE | G162: Georgia | H162: 44941.999 | I162: FALSE | J162: FALSE | K162: United States | L162: hour | M162: 0 | N162: 24 | O162: Sekon - 4.2 | P162: ['sas', 'sas', 'html', 'powerpoint', 'word', 'excel']
A163: Data Engineer | B163: IT Data Engineer | C163: Carol Stream, IL | D163: via Ai-Jobs.net | E163: Full-time | F163: FALSE | G163: California, United States | H163: 44933.504 | I163: FALSE | J163: TRUE | K163: United States | L163: year | M163: 98301.5 | N163: 0 | O163: ITW | P163: ['java', 'sql']
A164: Data Scientist | B164: Data Scientist | C164: Huntsville, AL | D164: via Indeed | E164: Full-time | F164: FALSE | G164: Illinois, United States | H164: 44930.587 | I164: FALSE | J164: FALSE | K164: United States | L164: year | M164: 120000.5 | N164: 0 | O164: SAIC | P164: ['sql', 'oracle']
A165: Data Scientist | B165: Data Scientist | For Educational Kids Science Company | C165: Anywhere | D165: via Indeed | E165: Full-time | F165: TRUE | G165: Texas, United States | H165: 44935.962 | I165: FALSE | J165: FALSE | K165: United States | L165: year | M165: 105000 | N165: 0 | O165: Generation Genius, Inc. | P165: ['spark']
A166: Senior Data Scientist | B166: Senior Manager, Data Science | C166: Petaling Jaya, Selangor, Malaysia | D166: via Ai-Jobs.net | E166: Full-time | F166: FALSE | G166: Malaysia | H166: 44940.058 | I166: FALSE | J166: FALSE | K166: Malaysia | L166: year | M166: 79200 | N166: 0 | O166: Western Digital | P166: ['r', 'python', 'spark', 'hadoop']
A167: Data Analyst | B167: Specialist, Customer Data Analytics | C167: Thousand Oaks, CA | D167: via ZipRecruiter | E167: Full-time | F167: FALSE | G167: California, United States | H167: 44928.917 | I167: FALSE | J167: TRUE | K167: United States | L167: year | M167: 57500 | N167: 0 | O167: Guitar Center Holdings | P167: ['sql', 'python', 'tableau', 'excel', 'microstrategy']
A168: Data Analyst | B168: Data Analyst | C168: Pasadena, CA | D168: via KHON2 Jobs | E168: Full-time | F168: FALSE | G168: California, United States | H168: 44937.668 | I168: TRUE | J168: TRUE | K168: United States | L168: hour | M168: 0 | N168: 46.860001 | O168: APR Consulting Inc | P168: ['sql', 'sas', 'sas', 'cobol', 'db2', 'excel']
A169: Data Analyst | B169: Data Analyst | C169: Ponte Vedra Beach, FL | D169: via LinkedIn | E169: Full-time | F169: FALSE | G169: Florida, United States | H169: 44931.585 | I169: FALSE | J169: FALSE | K169: United States | L169: year | M169: 60000 | N169: 0 | O169: Insight Global | P169: ['go', 'r', 'python', 'sql', 'numpy', 'pandas', 'jupyter', 'power bi', 'tableau', 'qlik']
A170: Software Engineer | B170: ETL Python Automation Tester | C170: Pune, Maharashtra, India | D170: via Ai-Jobs.net | E170: Full-time | F170: FALSE | G170: India | H170: 44936.603 | I170: FALSE | J170: FALSE | K170: India | L170: year | M170: 64800 | N170: 0 | O170: 1st-Recruit LLC | P170: 0
A171: Data Analyst | B171: Data Analyst/Custom Insights | C171: Kraków, Poland | D171: via Ai-Jobs.net | E171: Full-time | F171: FALSE | G171: Poland | H171: 44937.024 | I171: FALSE | J171: FALSE | K171: Poland | L171: year | M171: 45000 | N171: 0 | O171: Verisk | P171: ['sql', 'excel']
A172: Data Analyst | B172: Lead Data Analyst | C172: Atlanta, GA | D172: via LinkedIn | E172: Contractor | F172: FALSE | G172: Georgia | H172: 44944.741 | I172: FALSE | J172: FALSE | K172: United States | L172: year | M172: 112500 | N172: 0 | O172: Encore Technologies | P172: ['sql', 'r', 'python', 'sas', 'sas', 'nosql', 'scala', 'javascript', 'cassandra', 'redshift', 'snowflake', 'aws', 'spark', 'microstrategy', 'excel', 'spss']
A173: Senior Data Engineer | B173: Senior Data Engineer - Berlin | C173: Berlin, Germany | D173: via Ai-Jobs.net | E173: Full-time | F173: FALSE | G173: Germany | H173: 44951.333 | I173: FALSE | J173: FALSE | K173: Germany | L173: year | M173: 147500 | N173: 0 | O173: Typeform | P173: ['scala', 'python', 'sql', 'aws', 'redshift', 'gcp', 'bigquery', 'azure', 'snowflake', 'kafka', 'spark', 'airflow']
A174: Senior Data Engineer | B174: REMOTE Sr. Data Engineer | C174: Anywhere | D174: via Indeed | E174: Full-time | F174: TRUE | G174: Texas, United States | H174: 44930.568 | I174: FALSE | J174: TRUE | K174: United States | L174: year | M174: 155000 | N174: 0 | O174: CyberCoders | P174: ['python', 'sql', 'bigquery', 'airflow']
A175: Data Analyst | B175: Data Analyst - Tiktok Ads and Monetization Products | C175: Mountain View, CA | D175: via LinkedIn | E175: Full-time | F175: FALSE | G175: California, United States | H175: 44930.626 | I175: FALSE | J175: TRUE | K175: United States | L175: year | M175: 170000 | N175: 0 | O175: ByteDance | P175: ['sql', 'php', 'python', 'perl', 'tableau']
A176: Data Engineer | B176: Staff Data Engineer | C176: Waltham, MA | D176: via ZipRecruiter | E176: Full-time | F176: FALSE | G176: Illinois, United States | H176: 44955.84 | I176: TRUE | J176: FALSE | K176: United States | L176: year | M176: 160000 | N176: 0 | O176: National Grid (UK) | P176: ['sql', 'python', 'oracle', 'snowflake', 'gcp', 'aws', 'azure', 'spark', 'alteryx', 'tableau']
A177: Data Scientist | B177: Senior/Staff Data Scientist | C177: San Francisco, CA | D177: via Indeed | E177: Full-time | F177: FALSE | G177: California, United States | H177: 44929.773 | I177: FALSE | J177: TRUE | K177: United States | L177: year | M177: 250000 | N177: 0 | O177: Averity | P177: ['python', 'sql', 'scala', 'spark']
A178: Data Analyst | B178: Data Analyst/ $100M Valuation/ Benefits Fully Covered | C178: Georgia | D178: via LinkedIn | E178: Full-time | F178: FALSE | G178: Georgia | H178: 44935.903 | I178: FALSE | J178: TRUE | K178: United States | L178: year | M178: 145000 | N178: 0 | O178: Storm2 | P178: ['sql', 'mongodb', 'mongodb', 'nosql']
A179: Data Scientist | B179: ETL/Data Science Specialist | C179: Plano, TX | D179: via LinkedIn | E179: Contractor | F179: FALSE | G179: Texas, United States | H179: 44931.961 | I179: FALSE | J179: FALSE | K179: United States | L179: hour | M179: 0 | N179: 60 | O179: Insight Global | P179: ['sql', 'python', 'postgresql', 'airflow', 'kubernetes', 'docker']
A180: Senior Data Engineer | B180: Sr Data Engineer (REMOTE) | C180: Anywhere | D180: via Indeed | E180: Full-time | F180: TRUE | G180: Florida, United States | H180: 44930.611 | I180: FALSE | J180: FALSE | K180: United States | L180: year | M180: 135600 | N180: 0 | O180: The Hartford | P180: ['sql', 'python', 'oracle', 'aws', 'snowflake', 'linux', 'github']
...

Sheet Jan - Copy & Paste
A1: job_title_short | B1: job_title | C1: job_location | D1: job_via | E1: job_schedule_type | F1: job_work_from_home | G1: search_location | H1: job_posted_date | I1: job_no_degree_mention | J1: job_health_insurance | K1: job_country | L1: salary_rate | M1: salary_year_avg | N1: salary_hour_avg | O1: company_name | P1: job_skills
A2: Data Scientist | B2: Data Scientist - TikTok Ads | C2: Mountain View, CA | D2: via LinkedIn | E2: Full-time | F2: FALSE | G2: California, United States | H2: 44928.626 | I2: FALSE | J2: TRUE | K2: United States | L2: year | M2: 224500 | O2: TikTok | P2: ['r', 'python', 'matlab', 'sql']
A3: Data Scientist | B3: Data Scientist - Technical Platform | C3: Mountain View, CA | D3: via LinkedIn | E3: Full-time | F3: FALSE | G3: California, United States | H3: 44938.17 | I3: FALSE | J3: TRUE | K3: United States | L3: year | M3: 157500 | O3: TikTok | P3: ['sql', 'python']
A4: Data Scientist | B4: Data Scientist - Computer Vision | C4: Paris, France | D4: via Ai-Jobs.net | E4: Full-time | F4: FALSE | G4: France | H4: 44956.343 | I4: FALSE | J4: FALSE | K4: France | L4: year | M4: 88128 | O4: digiRocks | P4: ['python', 'c++', 'pytorch', 'tensorflow', 'keras']
A5: Data Scientist | B5: Senior Actuarial Consultant and Data Scientist - Remote | C5: Las Vegas, NV | D5: via Las Vegas, NV - Geebo | E5: Full-time | F5: FALSE | G5: California, United States | H5: 44953.004 | I5: FALSE | J5: TRUE | K5: United States | L5: hour | N5: 24 | O5: UnitedHealth Group | P5: ['r', 'python', 'vba', 'sas', 'sas', 'sql', 'databricks', 'excel']
A6: Data Scientist | B6: Data Scientist Digital Effectiveness Operations & Technology Analytics | C6: Sun City, AZ | D6: via ZipRecruiter | E6: Full-time | F6: FALSE | G6: California, United States | H6: 44955.42 | I6: FALSE | J6: TRUE | K6: United States | L6: year | M6: 105800 | O6: Cox Communications | P6: ['sql', 'python', 'aws', 'pandas', 'numpy', 'scikit-learn', 'pyspark', 'tableau']
A7: Data Scientist | B7: Data Scientist - Marketing Analytics | C7: Irving, TX | D7: via LinkedIn | E7: Full-time | F7: FALSE | G7: Texas, United States | H7: 44950.668 | I7: FALSE | J7: TRUE | K7: United States | L7: year | M7: 115000 | O7: Cottonwood Financial | P7: ['sql', 'sas', 'sas', 'python', 'r']
A8: Senior Data Analyst | B8: Senior Data Analyst Business Optimization Intelligence | C8: Bailey's Crossroads, VA | D8: via ZipRecruiter | E8: Full-time | F8: FALSE | G8: New York, United States | H8: 44930.417 | I8: FALSE | J8: TRUE | K8: United States | L8: year | M8: 96500 | O8: Cox Communications | P8: ['sql', 'snowflake', 'aws', 'microstrategy', 'tableau', 'excel']
A9: Data Engineer | B9: IT & Strategy Talent Programme - AI/ML and Data Engineer | C9: Hamburg, Germany | D9: via Ai-Jobs.net | E9: Full-time | F9: FALSE | G9: Germany | H9: 44938.864 | I9: FALSE | J9: FALSE | K9: Germany | L9: year | M9: 98301.5 | O9: Vattenfall | P9: ['azure']
A10: Senior Data Scientist | B10: Senior Data Scientist | C10: El Mirage, AZ | D10: via ZipRecruiter | E10: Full-time | F10: FALSE | G10: California, United States | H10: 44955.42 | I10: FALSE | J10: TRUE | K10: United States | L10: year | M10: 116700 | O10: Cox Communications | P10: ['sql', 'r', 'python', 'scala', 'java', 'c++', 'sas', 'sas', 'aws', 'spark', 'ggplot2', 'pandas', 'numpy', 'scikit-learn', 'tableau']
A11: Data Engineer | B11: Data Engineer | C11: Chicago, IL | D11: via Indeed | E11: Full-time | F11: FALSE | G11: California, United States | H11: 44939.798 | I11: FALSE | J11: TRUE | K11: United States | L11: year | M11: 102500 | O11: Alliant Credit Union | P11: ['sql', 'azure', 'tableau']
A12: Senior Data Scientist | B12: Senior Data Scientist | C12: Austin, TX | D12: via Indeed | E12: Full-time | F12: FALSE | G12: Texas, United States | H12: 44930.92 | I12: FALSE | J12: TRUE | K12: United States | L12: year | M12: 145000 | O12: CyberCoders | P12: ['python', 'azure', 'pytorch', 'tensorflow', 'opencv', 'datarobot']
A13: Data Engineer | B13: Systems & Data Engineer | C13: Boston, MA | D13: via LinkedIn | E13: Full-time | F13: FALSE | G13: Illinois, United States | H13: 44952.675 | I13: FALSE | J13: TRUE | K13: United States | L13: year | M13: 75000 | O13: New England Board of Higher Education | P13: ['sql', 'python', 'r', 'java', 'scala', 'aws', 'azure', 'tableau']
A14: Data Engineer | B14: Data Engineer | C14: Anywhere | D14: via LinkedIn | E14: Full-time | F14: TRUE | G14: Florida, United States | H14: 44944.634 | I14: TRUE | J14: FALSE | K14: United States | L14: year | M14: 105000 | O14: HirePlace | P14: ['no-sql', 'sql', 'python', 'scala', 'java', 'bash', 'powershell', 'azure', 'databricks', 'spark']
A15: Data Engineer | B15: Jr. Data Engineer | C15: Madison, WI | D15: via Ladders | E15: Full-time | F15: FALSE | G15: New York, United States | H15: 44935.087 | I15: FALSE | J15: FALSE | K15: United States | L15: year | M15: 90000 | O15: Baker Tilly | P15: ['sql', 'python', 'r', 'sql server', 'azure', 'databricks']
A16: Data Scientist | B16: Data Science Manager, Specialist Master - SFL Scientific | C16: San Jose, CA | D16: via Ladders | E16: Full-time | F16: FALSE | G16: California, United States | H16: 44946.515 | I16: FALSE | J16: FALSE | K16: United States | L16: year | M16: 200000 | O16: Deloitte | P16: ['python', 'aws', 'azure', 'gcp', 'keras', 'tensorflow', 'pytorch', 'pandas', 'scikit-learn', 'jupyter']
A17: Data Scientist | B17: Data Scientist I | C17: Boston, MA | D17: via ZipRecruiter | E17: Full-time | F17: FALSE | G17: New York, United States | H17: 44931.669 | I17: FALSE | J17: FALSE | K17: United States | L17: year | M17: 57500 | O17: Tresume and Asta CRS | P17: ['r', 'sql', 'python', 'scala', 'java', 'c++']
A18: Data Analyst | B18: Lead-Data Analyst | C18: St James, MO | D18: via My ArkLaMiss Jobs | E18: Full-time | F18: FALSE | G18: Illinois, United States | H18: 44928.751 | I18: FALSE | J18: TRUE | K18: United States | L18: year | M18: 144481.5 | O18: EDWARD JONES
A19: Data Scientist | B19: Data Science Instructor | C19: San Antonio, TX | D19: via LinkedIn | E19: Full-time | F19: FALSE | G19: Sudan | H19: 44936.752 | I19: FALSE | J19: TRUE | K19: Sudan | L19: year | M19: 77500 | O19: Codeup | P19: ['python', 'sql', 'matplotlib', 'seaborn', 'spark', 'hadoop', 'jupyter', 'tableau']
A20: Data Engineer | B20: Big Data Engineer | C20: Chicago, IL | D20: via LinkedIn | E20: Full-time | F20: FALSE | G20: Sudan | H20: 44952.328 | I20: FALSE | J20: FALSE | K20: Sudan | L20: year | M20: 105000 | O20: Robert Half | P20: ['python', 'sql', 'go', 'aws', 'databricks', 'spark', 'pyspark', 'airflow', 'alteryx', 'tableau']
A21: Data Analyst | B21: Institutional Credit Management - Lending Data Analyst - Vice... | C21: Pinellas Park, FL | D21: via ComputerWork | E21: Full-time | F21: FALSE | G21: Florida, United States | H21: 44951.669 | I21: FALSE | J21: FALSE | K21: United States | L21: year | M21: 132315 | O21: Citi | P21: ['cognos', 'tableau']
A22: Senior Data Scientist | B22: AI/ML - Senior Data Science Manager, AI/ML Data | C22: Cupertino, CA | D22: via My Champlain Valley Jobs | E22: Full-time | F22: FALSE | G22: California, United States | H22: 44938.754 | I22: FALSE | J22: TRUE | K22: United States | L22: year | M22: 173000 | O22: Apple
A23: Data Analyst | B23: Experian Data Analyst Remote / Telecommute Jobs | C23: Anywhere | D23: via Clearance Jobs | E23: Full-time | F23: TRUE | G23: New York, United States | H23: 44929.894 | I23: FALSE | J23: FALSE | K23: United States | L23: year | M23: 112500 | O23: Seneca Resources, LLC | P23: ['aws', 'linux']
A24: Data Scientist | B24: Electronics Data Scientist Intern | C24: Anywhere | D24: via Indeed | E24: Full-time | F24: TRUE | G24: California, United States | H24: 44953.379 | I24: FALSE | J24: FALSE | K24: United States | L24: hour | N24: 21.75 | O24: MilliporeSigma | P24: ['excel', 'outlook']
A25: Data Scientist | B25: Data Scientist (Genomics/Genetics, Python, AWS) - no c2c | C25: Anywhere | D25: via LinkedIn | E25: Contractor | F25: TRUE | G25: Texas, United States | H25: 44935.753 | I25: FALSE | J25: FALSE | K25: United States | L25: hour | N25: 66.5 | O25: neteffects | P25: ['python', 'r', 'sql', 'java', 'aws', 'gcp', 'airflow', 'docker', 'git', 'kubernetes']
A26: Senior Data Analyst | B26: Senior Data Analyst | C26: Ontario, CA | D26: via Indeed | E26: Full-time | F26: FALSE | G26: California, United States | H26: 44937.418 | I26: FALSE | J26: TRUE | K26: United States | L26: hour | N26: 34.875 | O26: Prime Healthcare Management Inc | P26: ['sql', 'excel']
A27: Data Analyst | B27: Data Analyst (Remote) | C27: Anywhere | D27: via Indeed | E27: Full-time | F27: TRUE | G27: Georgia | H27: 44940.405 | I27: FALSE | J27: FALSE | K27: United States | L27: year | M27: 52500 | O27: Acosta, Inc. | P27: ['windows', 'excel', 'word', 'powerpoint', 'power bi']
A28: Data Engineer | B28: Sr. Data Engineer | C28: Austin, TX | D28: via Indeed | E28: Full-time | F28: FALSE | G28: Georgia | H28: 44947.598 | I28: TRUE | J28: FALSE | K28: United States | L28: year | M28: 164500 | O28: Charles Schwab | P28: ['sql', 'python', 'java', 'gcp', 'bigquery', 'aws', 'vmware', 'pandas', 'spark', 'airflow', 'kafka', 'splunk', 'tableau', 'jira', 'confluence']
A29: Data Engineer | B29: Scientific Data Engineer (Remote Friendly) | C29: Anywhere | D29: via LinkedIn | E29: Full-time | F29: TRUE | G29: Texas, United States | H29: 44951.975 | I29: FALSE | J29: FALSE | K29: United States | L29: year | M29: 149874 | O29: Berkeley Lab | P29: ['python', 'java', 'javascript', 'bash', 'nosql', 'mysql', 'oracle', 'aws', 'linux']
A30: Data Analyst | B30: Lead Business Data Analyst - Global Delivery Services | C30: Santa Fe, NM | D30: via DirectlyApply | E30: Full-time | F30: FALSE | G30: Sudan | H30: 44932.163 | I30: TRUE | J30: FALSE | K30: Sudan | L30: year | M30: 115775 | O30: UKG (Ultimate Kronos Group) | P30: ['power bi', 'excel', 'tableau']
A31: Senior Data Analyst | B31: Senior Data Analyst - Cox Communities | C31: Oakton, VA | D31: via ZipRecruiter | E31: Full-time | F31: FALSE | G31: New York, United States | H31: 44930.417 | I31: FALSE | J31: TRUE | K31: United States | L31: year | M31: 96500 | O31: Cox Communications | P31: ['sql', 'alteryx', 'tableau']
A32: Senior Data Scientist | B32: Senior Data Scientist , Health Equity – Chicago, Boston, OR Remote | C32: Anywhere | D32: via Indeed | E32: Full-time | F32: TRUE | G32: Illinois, United States | H32: 44942.905 | I32: FALSE | J32: TRUE | K32: United States | L32: year | M32: 135000 | O32: CVS Health | P32: ['python', 'sql', 'gcp', 'azure', 'aws', 'hadoop']
A33: Data Scientist | B33: Manufacturing Data Scientist | C33: Englewood, CO | D33: via Indeed | E33: Full-time | F33: FALSE | G33: Sudan | H33: 44939.891 | I33: FALSE | J33: FALSE | K33: Sudan | L33: year | M33: 110000 | O33: Scytec Consulting Inc. | P33: ['sql', 'nosql', 'mongodb', 'mongodb', 'c#', 'sql server', 'azure', 'aws', 'git']
A34: Data Engineer | B34: Data Engineer | C34: New York, NY | D34: via LinkedIn | E34: Full-time | F34: FALSE | G34: Texas, United States | H34: 44950.632 | I34: FALSE | J34: FALSE | K34: United States | L34: year | M34: 155000 | O34: Revel IT | P34: ['sql', 'nosql', 'python', 'ruby', 'ruby', 'mysql', 'redshift', 'aws', 'tableau']
A35: Data Scientist | B35: Mathematics Statistician or Statistician (Data Scientist) 12 Month... | C35: Buffalo, NY | D35: via Buffalo, NY - Geebo | E35: Full-time | F35: FALSE | G35: Illinois, United States | H35: 44942.003 | I35: FALSE | J35: TRUE | K35: United States | L35: hour | N35: 24 | O35: Internal Revenue Service | P35: ['c', 'r', 'python', 'sql', 'java', 'oracle']
A36: Data Analyst | B36: Data Analyst | D36: via LinkedIn | E36: Full-time | F36: FALSE | G36: New York, United States | H36: 44929.686 | I36: TRUE | J36: FALSE | K36: United States | L36: year | M36: 97500 | O36: Robert Half | P36: ['sql', 't-sql', 'sql server', 'azure', 'ssrs', 'ssis']
A37: Data Engineer | B37: Data Engineer | C37: Washington, DC | D37: via PHL17 Jobs | E37: Full-time | F37: FALSE | G37: Georgia | H37: 44941.583 | I37: FALSE | J37: FALSE | K37: United States | L37: year | M37: 145000 | O37: Peraton | P37: ['python', 'sql', 'neo4j', 'mysql', 'aws', 'spark', 'express', 'splunk', 'git', 'jira', 'confluence']
A38: Data Engineer | B38: Data Engineer - A4370 | C38: Pleasanton, CA | D38: via Ai-Jobs.net | E38: Full-time | F38: FALSE | G38: California, United States | H38: 44937.839 | I38: FALSE | J38: TRUE | K38: United States | L38: year | M38: 147500 | O38: Nisum | P38: ['sql', 'spark']
A39: Senior Data Engineer | B39: Senior Data Engineer | C39: Woonsocket, RI | D39: via Indeed | E39: Full-time | F39: FALSE | G39: Illinois, United States | H39: 44933.921 | I39: FALSE | J39: TRUE | K39: United States | L39: year | M39: 135000 | O39: CVS Health | P39: ['sql', 'python', 'bash', 'oracle', 'snowflake', 'azure', 'gcp', 'hadoop']
A40: Senior Data Analyst | B40: Senior Data Analyst, Business Optimization | C40: Smyrna, GA | D40: via ZipRecruiter | E40: Full-time | F40: FALSE | G40: Georgia | H40: 44953.436 | I40: FALSE | J40: TRUE | K40: United States | L40: year | M40: 96500 | O40: Cox Communications | P40: ['swift', 'sql', 'excel', 'powerpoint', 'microstrategy', 'tableau']
A41: Data Engineer | B41: Data Engineer | C41: Malvern, PA | D41: via Dice | E41: Full-time | F41: FALSE | G41: Georgia | H41: 44935.863 | I41: TRUE | J41: FALSE | K41: United States | L41: year | M41: 70000 | O41: Acadia Technologies, Inc. | P41: ['pyspark']
A42: Senior Data Scientist | B42: Senior Data Scientist - ProServe | C42: Lakeland, FL | D42: via Lakeland, FL - Geebo | E42: Full-time | F42: FALSE | G42: Florida, United States | H42: 44929.983 | I42: FALSE | J42: FALSE | K42: United States | L42: hour | N42: 24 | O42: Amazon Web Services, Inc. | P42: ['aws', 'mxnet', 'tensorflow', 'pytorch', 'scikit-learn']
A43: Senior Data Analyst | B43: Senior Data Analyst | C43: New York, NY | D43: via LinkedIn | E43: Full-time | F43: FALSE | G43: New York, United States | H43: 44930.061 | I43: FALSE | J43: TRUE | K43: United States | L43: year | M43: 170000 | O43: Harnham | P43: ['sql', 'python', 'r', 'tableau', 'power bi', 'looker']
A44: Machine Learning Engineer | B44: Senior Machine Learning Engineer / Python Developer | C44: Lviv, Lviv Oblast, Ukraine | D44: via Ai-Jobs.net | E44: Full-time | F44: FALSE | G44: Ukraine | H44: 44945.193 | I44: FALSE | J44: FALSE | K44: Ukraine | L44: year | M44: 104668 | O44: LoopMe | P44: ['python', 'r', 'elasticsearch', 'airflow', 'spark', 'kafka']
A45: Data Engineer | B45: Cloud Data Engineer | C45: Broomfield, CO | D45: via LinkedIn | E45: Full-time | F45: FALSE | G45: Sudan | H45: 44951.916 | I45: FALSE | J45: TRUE | K45: Sudan | L45: year | M45: 125000 | O45: Noodles & Company | P45: ['python', 'sql', 'bigquery', 'gcp', 'power bi', 'git']
A46: Data Scientist | B46: Engineering Data Scientist, Ad Ranking | C46: New York, NY | D46: via Ladders | E46: Full-time | F46: FALSE | G46: New York, United States | H46: 44941.252 | I46: FALSE | J46: TRUE | K46: United States | L46: year | M46: 350000 | O46: Snap Inc | P46: ['sql', 'python', 'r', 'express']
A47: Machine Learning Engineer | B47: Senior AI Research Scientist | C47: Lisbon, Portugal | D47: via Ai-Jobs.net | E47: Full-time | F47: FALSE | G47: Portugal | H47: 44935.885 | I47: FALSE | J47: FALSE | K47: Portugal | L47: year | M47: 94342.5 | O47: Unbabel | P47: ['python', 'c++', 'pytorch', 'tensorflow']
A48: Data Engineer | B48: Lead Business Intelligence / Data Engineer: | C48: Brentwood, TN | D48: via LinkedIn | E48: Full-time | F48: FALSE | G48: Illinois, United States | H48: 44932.798 | I48: FALSE | J48: FALSE | K48: United States | L48: year | M48: 127500 | O48: Robert Half | P48: ['python', 'r', 't-sql', 'sql', 'go', 'oracle', 'jupyter', 'jquery', 'sharepoint', 'jenkins', 'docker', 'confluence']
A49: Data Scientist | B49: Staff Data Scientist | C49: Mountain View, CA | D49: via IT JobServe | E49: Full-time | F49: FALSE | G49: California, United States | H49: 44928.794 | I49: FALSE | J49: TRUE | K49: United States | L49: year | M49: 202500 | O49: CyberCoders | P49: ['python', 'java', 'scala', 'sql', 'aws', 'hadoop', 'spark', 'kafka', 'word']
A50: Data Engineer | B50: Quality Engineering Manager (Data) | C50: Waltham, MA | D50: via ZipRecruiter | E50: Full-time | F50: FALSE | G50: Sudan | H50: 44935.483 | I50: FALSE | J50: FALSE | K50: Sudan | L50: year | M50: 150000 | O50: National Grid (UK) | P50: ['sql', 'snowflake', 'power bi', 'ssrs']
A51: Senior Data Engineer | B51: Senior Data Engineer- Remote | C51: Frisco, TX | D51: via My ArkLaMiss Jobs | E51: Full-time | F51: FALSE | G51: Georgia | H51: 44938.39 | I51: FALSE | J51: TRUE | K51: United States | L51: year | M51: 138200 | O51: The Hartford | P51: ['python', 'aws', 'hadoop', 'spark']
A52: Data Analyst | B52: Sr Data Analyst | C52: Florham Park, NJ | D52: via LinkedIn | E52: Full-time | F52: FALSE | G52: New York, United States | H52: 44931.709 | I52: FALSE | J52: TRUE | K52: United States | L52: year | M52: 127500 | O52: Sompo International | P52: ['sql', 'sql server', 'db2', 'sap']
A53: Data Engineer | B53: Big Data Engineer | C53: Malvern, PA | D53: via LinkedIn | E53: Contractor | F53: FALSE | G53: Texas, United States | H53: 44956.798 | I53: FALSE | J53: FALSE | K53: United States | L53: hour | N53: 61.5 | O53: Robert Half | P53: ['sql', 'go', 'snowflake', 'ssis']
A54: Senior Data Engineer | B54: Senior Data Engineer- Uhaul Data ( Remote Eligible) | C54: Richmond, VA | D54: via WJTV Jobs | E54: Full-time | F54: FALSE | G54: New York, United States | H54: 44953.673 | I54: FALSE | J54: TRUE | K54: United States | L54: year | M54: 170672 | O54: Capital One | P54: ['java', 'scala', 'python', 'nosql', 'sql', 'mongo', 'shell', 'mysql', 'cassandra', 'redshift', 'snowflake', 'aws', 'azure', 'hadoop', 'kafka', 'spark']
A55: Data Engineer | B55: Data Engineer | C55: Springfield, VA | D55: via Ladders | E55: Full-time | F55: FALSE | G55: Florida, United States | H55: 44928.506 | I55: FALSE | J55: FALSE | K55: United States | L55: year | M55: 115000 | O55: National Geospatial-Intelligence Agency | P55: ['go', 'python', 'r', 'java', 'c', 'nosql', 'mongodb', 'mongodb', 'elasticsearch', 'mysql', 'postgresql', 'neo4j', 'oracle', 'aws', 'sap', 'terraform', 'ansible']
A56: Senior Data Engineer | B56: Senior Data Engineer ETL/Oracle | C56: Denver, CO | D56: via Ladders | E56: Full-time | F56: FALSE | G56: Illinois, United States | H56: 44953.3 | I56: FALSE | J56: TRUE | K56: United States | L56: year | M56: 150000 | O56: TIAA | P56: ['shell', 'java', 'oracle', 'snowflake', 'unix', 'splunk', 'flow', 'git']
A57: Data Scientist | B57: VP, Data Science | C57: United States | D57: via My ArkLaMiss Jobs | E57: Full-time | F57: FALSE | G57: Sudan | H57: 44946.081 | I57: FALSE | J57: FALSE | K57: Sudan | L57: year | M57: 265500 | O57: MediaMath | P57: ['python', 'scala', 'spark']
A58: Data Engineer | B58: Staff / Principal Data Engineer | C58: Anywhere | D58: via LinkedIn | E58: Full-time | F58: TRUE | G58: Georgia | H58: 44951.569 | I58: FALSE | J58: TRUE | K58: United States | L58: year | M58: 155000 | O58: Prestige Staffing | P58: ['sql', 'azure', 'puppet', 'terraform', 'jenkins']
A59: Data Engineer | B59: Principal Data Engineer | C59: Arlington Heights, IL | D59: via Dice | E59: Full-time | F59: FALSE | G59: Illinois, United States | H59: 44936.048 | I59: FALSE | J59: TRUE | K59: United States | L59: year | M59: 145000 | O59: Jobot | P59: ['scala', 'java', 'python', 'cassandra', 'databricks', 'azure', 'aws', 'spark', 'kafka', 'kubernetes', 'docker']
A60: Data Scientist | B60: Data Scientist II | C60: California | D60: via Farmers District Office - Talentify | E60: Full-time | F60: FALSE | G60: California, United States | H60: 44944.001 | I60: FALSE | J60: TRUE | K60: United States | L60: year | M60: 135000 | O60: Farmers Insurance | P60: ['sql', 'python', 'c++', 'ssis', 'tableau']
A61: Senior Data Engineer | B61: AWS Senior Cloud Data Engineer | C61: Anywhere | D61: via Upwork | E61: Contractor | F61: TRUE | G61: California, United States | H61: 44936.35 | I61: TRUE | J61: FALSE | K61: United States | L61: hour | N61: 16.5 | O61: Upwork | P61: ['aws', 'redshift', 'git']
A62: Data Analyst | B62: Data Capabilities Analyst | C62: Irving, TX | D62: via Ladders | E62: Full-time | F62: FALSE | G62: Texas, United States | H62: 44930.437 | I62: FALSE | J62: FALSE | K62: United States | L62: year | M62: 115000 | O62: Citigroup, Inc | P62: ['excel', 'powerpoint']
A63: Data Engineer | B63: Senior Data Engineer II | C63: Los Angeles, CA | D63: via Ladders | E63: Full-time | F63: FALSE | G63: Illinois, United States | H63: 44931.354 | I63: TRUE | J63: FALSE | K63: United States | L63: year | M63: 90000 | O63: McKinsey & Company | P63: ['python', 'sql', 'databricks', 'snowflake', 'aws', 'gcp', 'azure', 'pyspark', 'airflow', 'kafka', 'docker', 'kubernetes']
A64: Senior Data Analyst | B64: Senior Game Data Analyst - Tarboosh Studio | C64: Paris, France | D64: via Ai-Jobs.net | E64: Full-time | F64: FALSE | G64: France | H64: 44949.925 | I64: TRUE | J64: FALSE | K64: France | L64: year | M64: 111175 | O64: Voodoo | P64: ['sql', 'r', 'python']
A65: Senior Data Engineer | B65: Senior Data Engineer | C65: DeSoto, TX | D65: via Ladders | E65: Full-time | F65: FALSE | G65: Georgia | H65: 44930.442 | I65: FALSE | J65: TRUE | K65: United States | L65: year | M65: 150000 | O65: Caterpillar, Inc | P65: ['sql', 'nosql', 'python', 'ruby', 'ruby', 'java']
A66: Data Engineer | B66: ERP Data Engineer | C66: Lansing, MI | D66: via LinkedIn | E66: Full-time | F66: FALSE | G66: Sudan | H66: 44936.71 | I66: FALSE | J66: FALSE | K66: Sudan | L66: year | M66: 80000 | O66: Venteon | P66: ['sql', 'sap']
A67: Data Scientist | B67: Head of Data Science | C67: Anywhere | D67: via LinkedIn | E67: Full-time | F67: TRUE | G67: Sudan | H67: 44930.581 | I67: FALSE | J67: TRUE | K67: Sudan | L67: year | M67: 215000 | O67: Lawrence Harvey
A68: Senior Data Analyst | B68: Sr Data Analyst | $90k | Lake Forest, IL | C68: Lake Forest, IL | D68: via Recruit.net | E68: Full-time | F68: FALSE | G68: Illinois, United States | H68: 44949.002 | I68: TRUE | J68: FALSE | K68: United States | L68: year | M68: 90000 | O68: Trinity Intl.
A69: Data Analyst | B69: SQL Developer/Data Analyst | C69: New York, NY | D69: via Dice | E69: Contractor | F69: FALSE | G69: New York, United States | H69: 44956.542 | I69: FALSE | J69: FALSE | K69: United States | L69: hour | N69: 60 | O69: Infosight Consulting Inc | P69: ['sql', 'python', 'sql server', 'oracle']
A70: Data Scientist | B70: Data Analyst / Data Scientist | C70: Anywhere | D70: via Y Combinator | E70: Full-time | F70: TRUE | G70: California, United States | H70: 44946.723 | I70: FALSE | J70: TRUE | K70: United States | L70: year | M70: 160000 | O70: Y Combinator | P70: ['sql', 'python']
A71: Data Analyst | B71: Data Analyst with FinTech- | C71: Austin, TX | D71: via Austin, TX - Geebo | E71: Full-time | F71: FALSE | G71: Texas, United States | H71: 44942.001 | I71: TRUE | J71: FALSE | K71: United States | L71: hour | N71: 24 | O71: EXPERIS | P71: ['sql', 'snowflake']
A72: Senior Data Scientist | B72: Senior Data Scientist | C72: Austin, TX | D72: via LinkedIn | E72: Full-time | F72: FALSE | G72: Texas, United States | H72: 44937.962 | I72: FALSE | J72: TRUE | K72: United States | L72: year | M72: 160000 | O72: Primis | P72: ['python', 'sql', 'tableau']
A73: Senior Data Engineer | B73: Senior IT Data Engineer | C73: Fort Meade, MD | D73: via Ladders | E73: Full-time | F73: FALSE | G73: Georgia | H73: 44948.418 | I73: FALSE | J73: TRUE | K73: United States | L73: year | M73: 150000 | O73: Leidos | P73: ['python', 'java', 'kafka', 'linux', 'ansible', 'flow']
A74: Senior Data Engineer | B74: Senior Data Engineer | C74: San Diego, CA | D74: via LinkedIn | E74: Full-time | F74: FALSE | G74: Illinois, United States | H74: 44932.715 | I74: FALSE | J74: TRUE | K74: United States | L74: year | M74: 140000 | O74: Robert Half | P74: ['python', 'sql', 'nosql', 'azure', 'oracle', 'databricks', 'phoenix']
A75: Data Engineer | B75: Data Engineer | C75: Anywhere | D75: via Robert Half | E75: Full-time | F75: TRUE | G75: New York, United States | H75: 44935.588 | I75: TRUE | J75: FALSE | K75: United States | L75: year | M75: 140000 | O75: Robert Half | P75: ['python', 'sql', 'java', 't-sql', 'oracle', 'spark', 'pyspark', 'kafka', 'airflow', 'linux', 'sap', 'github']
A76: Senior Data Scientist | B76: Senior Data Scientist | C76: Foster City, CA | D76: via Ai-Jobs.net | E76: Full-time | F76: FALSE | G76: California, United States | H76: 44932.253 | I76: FALSE | J76: TRUE | K76: United States | L76: year | M76: 161000 | O76: Visa | P76: ['python', 'r', 'sql', 'spark', 'jupyter', 'word', 'excel', 'powerpoint']
A77: Data Engineer | B77: Data Engineer | C77: Anywhere | D77: via Indeed | E77: Full-time | F77: TRUE | G77: California, United States | H77: 44957.671 | I77: FALSE | J77: FALSE | K77: United States | L77: year | M77: 85000 | O77: DBSI Services | P77: ['sql', 'visual basic', 'oracle']
A78: Data Analyst | B78: Data Analyst | C78: McLean, VA | D78: via LinkedIn | E78: Contractor | F78: FALSE | G78: New York, United States | H78: 44937.667 | I78: TRUE | J78: FALSE | K78: United States | L78: hour | N78: 40 | O78: Mindlance | P78: ['python', 'sql', 'postgresql', 'aws', 'tableau']
A79: Data Engineer | B79: Data Engineer | C79: Anywhere | D79: via LinkedIn | E79: Full-time | F79: TRUE | G79: Canada | H79: 44950.01 | I79: FALSE | J79: FALSE | K79: Canada | L79: year | M79: 124000 | O79: GRIN | P79: ['python', 'sql', 'no-sql', 'bigquery', 'snowflake', 'airflow', 'kafka', 'spark']
A80: Data Scientist | B80: Mathematical Statistician (Data Scientist) or Statistician (Data... | C80: Charlotte, NC | D80: via DiversityJobs | E80: Full-time | F80: FALSE | G80: Illinois, United States | H80: 44937.379 | I80: FALSE | J80: TRUE | K80: United States | L80: year | M80: 143910.5 | O80: Internal Revenue Service | P80: ['c']
A81: Data Scientist | B81: Jr. Data Scientist | C81: Anywhere | D81: via LinkedIn | E81: Full-time | F81: TRUE | G81: Texas, United States | H81: 44939.921 | I81: FALSE | J81: FALSE | K81: United States | L81: year | M81: 75000 | O81: Take2 Consulting, LLC | P81: ['python', 'r', 'aws', 'gcp', 'tableau', 'git', 'github', 'jenkins', 'jira']
A82: Senior Data Engineer | B82: Senior Data Engineer | C82: Anywhere | D82: via LinkedIn | E82: Full-time | F82: TRUE | G82: Florida, United States | H82: 44939.591 | I82: FALSE | J82: FALSE | K82: United States | L82: year | M82: 150000 | O82: Alldus | P82: ['python', 'aws']
A83: Senior Data Scientist | B83: Senior Data Scientist | C83: Dayton, OH | D83: via Indeed | E83: Full-time | F83: FALSE | G83: Illinois, United States | H83: 44932.587 | I83: FALSE | J83: TRUE | K83: United States | L83: year | M83: 140000 | O83: Illumination Works | P83: ['python', 'mongodb', 'mongodb', 'neo4j', 'databricks', 'snowflake', 'azure', 'aws', 'pandas', 'numpy', 'scikit-learn', 'pytorch', 'tensorflow', 'keras', 'pyspark', 'hadoop', 'git']
A84: Data Engineer | B84: Azure Data Engineer / Datawarehouse Consultant | C84: Anywhere | D84: via LinkedIn | E84: Full-time | F84: TRUE | G84: New York, United States | H84: 44930.88 | I84: FALSE | J84: FALSE | K84: United States | L84: hour | N84: 85 | O84: Medix Technology | P84: ['sql', 'azure', 'oracle', 'databricks', 'ssis']
A85: Data Scientist | B85: Data Scientist, CX Strategy and Enablement (Austin, TX) | C85: Austin, TX | D85: via Built In Austin | E85: Full-time | F85: FALSE | G85: Sudan | H85: 44937.451 | I85: FALSE | J85: TRUE | K85: Sudan | L85: year | M85: 137110 | O85: LogicMonitor | P85: ['python', 'r', 'scala', 'looker', 'excel']
A86: Data Engineer | B86: Data Engineer | C86: California | D86: via LinkedIn | E86: Full-time | F86: FALSE | G86: California, United States | H86: 44957.588 | I86: FALSE | J86: FALSE | K86: United States | L86: year | M86: 110000 | O86: Northbound Executive Search | P86: ['python', 'java', 'sql', 'azure', 'snowflake', 'databricks']
A87: Senior Data Scientist | B87: Data Scientist/Senior Data Scientist | C87: Anywhere | D87: via LinkedIn | E87: Full-time | F87: TRUE | G87: Sudan | H87: 44936.71 | I87: FALSE | J87: FALSE | K87: Sudan | L87: year | M87: 165000 | O87: Harnham | P87: ['python', 'sql', 'git']
A88: Data Engineer | B88: Lead Data Engineer | C88: Anywhere | D88: via LinkedIn | E88: Full-time | F88: TRUE | G88: Illinois, United States | H88: 44952.925 | I88: FALSE | J88: TRUE | K88: United States | L88: year | M88: 165000 | O88: Intelletec | P88: ['python', 'sql', 'redshift', 'aws']
A89: Data Engineer | B89: Data engineer | C89: Anywhere | D89: via Upwork | E89: Contractor | F89: TRUE | G89: California, United States | H89: 44932.186 | I89: TRUE | J89: FALSE | K89: United States | L89: hour | N89: 60 | O89: Upwork | P89: ['python']
A90: Data Engineer | B90: Data Engineer - Mid Level | C90: Weston, TX | D90: via WREG Jobs | E90: Full-time | F90: FALSE | G90: Florida, United States | H90: 44928.631 | I90: FALSE | J90: TRUE | K90: United States | L90: year | M90: 123600 | O90: USAA | P90: ['sql', 'python', 'snowflake', 'phoenix']
A91: Data Scientist | B91: Working Student in Data Science for (e-)Mobility Cloud Solutions... | C91: Cluj-Napoca, Romania | D91: via Ai-Jobs.net | E91: Full-time | F91: FALSE | G91: Romania | H91: 44953.715 | I91: FALSE | J91: FALSE | K91: Romania | L91: year | M91: 56700 | O91: Bosch Group | P91: ['python', 'mongo', 'sql', 'azure', 'spark', 'hadoop', 'pandas', 'numpy', 'seaborn', 'docker', 'git']
A92: Data Engineer | B92: Data Engineer | C92: Zürich, Switzerland | D92: via Ai-Jobs.net | E92: Full-time | F92: FALSE | G92: Switzerland | H92: 44937.245 | I92: FALSE | J92: FALSE | K92: Switzerland | L92: year | M92: 147500 | O92: Capco | P92: ['python', 'shell', 'aws', 'kafka', 'pyspark', 'hadoop', 'spark', 'django', 'tableau', 'jenkins', 'ansible', 'chef', 'kubernetes', 'docker']
A93: Data Analyst | B93: Data Analyst | C93: Bethesda, MD | D93: via Ladders | E93: Full-time | F93: FALSE | G93: New York, United States | H93: 44942.386 | I93: FALSE | J93: FALSE | K93: United States | L93: year | M93: 175000 | O93: Xator Corp | P93: ['sql', 'r', 'python', 'excel', 'tableau', 'ms access']
A94: Data Scientist | B94: SAS Data Scientist | C94: Anywhere | D94: via Indeed | E94: Full-time | F94: TRUE | G94: Sudan | H94: 44939.099 | I94: FALSE | J94: TRUE | K94: Sudan | L94: year | M94: 99790 | O94: Tista Science and Technology Corporation | P94: ['vba', 'sas', 'sas', 'r', 'sql', 'db2', 'sql server', 'windows', 'unix']
A95: Data Scientist | B95: Lead Data Scientist, Gas Load Forecasting, Load Forecasting ... | C95: Hicksville, NY | D95: via KHON2 Jobs | E95: Full-time | F95: FALSE | G95: New York, United States | H95: 44940.752 | I95: FALSE | J95: FALSE | K95: United States | L95: year | M95: 128500 | O95: NATIONAL GRID CO USA (NE POWER) | P95: ['r', 'python', 'sql', 'excel']
A96: Data Scientist | B96: Data Scientist, Analytics - Trust & Safety | C96: San Jose, CA | D96: via LinkedIn | E96: Full-time | F96: FALSE | G96: California, United States | H96: 44953.462 | I96: FALSE | J96: TRUE | K96: United States | L96: year | M96: 209955.5 | O96: TikTok | P96: ['sql']
A97: Data Analyst | B97: Data Management Governance Analyst | C97: Hawaiian Gardens, CA | D97: via Ladders | E97: Full-time | F97: FALSE | G97: California, United States | H97: 44931.459 | I97: FALSE | J97: FALSE | K97: United States | L97: year | M97: 115000 | O97: NTT DATA Services | P97: ['sql', 'r', 'python', 'oracle', 'tableau', 'power bi', 'alteryx', 'flow']
A98: Data Analyst | B98: Senior, Data Analyst (Channel Analytics) | C98: Seoul, South Korea | D98: via Ai-Jobs.net | E98: Full-time | F98: FALSE | G98: South Korea | H98: 44944.734 | I98: FALSE | J98: FALSE | K98: South Korea | L98: year | M98: 111175 | O98: Coupang | P98: ['r', 'python', 'airflow', 'tableau', 'github', 'jira', 'confluence']
A99: Data Engineer | B99: Lead Data Engineer | C99: Floral Park, NY | D99: via KHON2 Jobs | E99: Full-time | F99: FALSE | G99: Illinois, United States | H99: 44953.675 | I99: FALSE | J99: TRUE | K99: United States | L99: year | M99: 208114 | O99: Capital One | P99: ['java', 'scala', 'python', 'nosql', 'sql', 'mongo', 'shell', 'mysql', 'cassandra', 'redshift', 'snowflake', 'aws', 'azure', 'hadoop', 'kafka', 'spark']
A100: Data Analyst | B100: Market Data Analyst f/m | C100: Egypt | D100: via Ai-Jobs.net | E100: Full-time | F100: FALSE | G100: Egypt | H100: 44945.306 | I100: FALSE | J100: FALSE | K100: Egypt | L100: year | M100: 51014 | O100: Bosch Group | P100: ['r', 'sql', 'python', 'spark', 'tableau', 'excel']
...

Sheet Jan - Move or Copy
A1: job_title_short | B1: job_title | C1: job_location | D1: job_via | E1: job_schedule_type | F1: job_work_from_home | G1: search_location | H1: job_posted_date | I1: job_no_degree_mention | J1: job_health_insurance | K1: job_country | L1: salary_rate | M1: salary_year_avg | N1: salary_hour_avg | O1: company_name | P1: job_skills
A2: Data Scientist | B2: Data Scientist - TikTok Ads | C2: Mountain View, CA | D2: via LinkedIn | E2: Full-time | F2: FALSE | G2: California, United States | H2: 44928.626 | I2: FALSE | J2: TRUE | K2: United States | L2: year | M2: 224500 | O2: TikTok | P2: ['r', 'python', 'matlab', 'sql']
A3: Data Scientist | B3: Data Scientist - Technical Platform | C3: Mountain View, CA | D3: via LinkedIn | E3: Full-time | F3: FALSE | G3: California, United States | H3: 44938.17 | I3: FALSE | J3: TRUE | K3: United States | L3: year | M3: 157500 | O3: TikTok | P3: ['sql', 'python']
A4: Data Scientist | B4: Data Scientist - Computer Vision | C4: Paris, France | D4: via Ai-Jobs.net | E4: Full-time | F4: FALSE | G4: France | H4: 44956.343 | I4: FALSE | J4: FALSE | K4: France | L4: year | M4: 88128 | O4: digiRocks | P4: ['python', 'c++', 'pytorch', 'tensorflow', 'keras']
A5: Data Scientist | B5: Senior Actuarial Consultant and Data Scientist - Remote | C5: Las Vegas, NV | D5: via Las Vegas, NV - Geebo | E5: Full-time | F5: FALSE | G5: California, United States | H5: 44953.004 | I5: FALSE | J5: TRUE | K5: United States | L5: hour | N5: 24 | O5: UnitedHealth Group | P5: ['r', 'python', 'vba', 'sas', 'sas', 'sql', 'databricks', 'excel']
A6: Data Scientist | B6: Data Scientist Digital Effectiveness Operations & Technology Analytics | C6: Sun City, AZ | D6: via ZipRecruiter | E6: Full-time | F6: FALSE | G6: California, United States | H6: 44955.42 | I6: FALSE | J6: TRUE | K6: United States | L6: year | M6: 105800 | O6: Cox Communications | P6: ['sql', 'python', 'aws', 'pandas', 'numpy', 'scikit-learn', 'pyspark', 'tableau']
A7: Data Scientist | B7: Data Scientist - Marketing Analytics | C7: Irving, TX | D7: via LinkedIn | E7: Full-time | F7: FALSE | G7: Texas, United States | H7: 44950.668 | I7: FALSE | J7: TRUE | K7: United States | L7: year | M7: 115000 | O7: Cottonwood Financial | P7: ['sql', 'sas', 'sas', 'python', 'r']
A8: Senior Data Analyst | B8: Senior Data Analyst Business Optimization Intelligence | C8: Bailey's Crossroads, VA | D8: via ZipRecruiter | E8: Full-time | F8: FALSE | G8: New York, United States | H8: 44930.417 | I8: FALSE | J8: TRUE | K8: United States | L8: year | M8: 96500 | O8: Cox Communications | P8: ['sql', 'snowflake', 'aws', 'microstrategy', 'tableau', 'excel']
A9: Data Engineer | B9: IT & Strategy Talent Programme - AI/ML and Data Engineer | C9: Hamburg, Germany | D9: via Ai-Jobs.net | E9: Full-time | F9: FALSE | G9: Germany | H9: 44938.864 | I9: FALSE | J9: FALSE | K9: Germany | L9: year | M9: 98301.5 | O9: Vattenfall | P9: ['azure']
A10: Senior Data Scientist | B10: Senior Data Scientist | C10: El Mirage, AZ | D10: via ZipRecruiter | E10: Full-time | F10: FALSE | G10: California, United States | H10: 44955.42 | I10: FALSE | J10: TRUE | K10: United States | L10: year | M10: 116700 | O10: Cox Communications | P10: ['sql', 'r', 'python', 'scala', 'java', 'c++', 'sas', 'sas', 'aws', 'spark', 'ggplot2', 'pandas', 'numpy', 'scikit-learn', 'tableau']
A11: Data Engineer | B11: Data Engineer | C11: Chicago, IL | D11: via Indeed | E11: Full-time | F11: FALSE | G11: California, United States | H11: 44939.798 | I11: FALSE | J11: TRUE | K11: United States | L11: year | M11: 102500 | O11: Alliant Credit Union | P11: ['sql', 'azure', 'tableau']
A12: Senior Data Scientist | B12: Senior Data Scientist | C12: Austin, TX | D12: via Indeed | E12: Full-time | F12: FALSE | G12: Texas, United States | H12: 44930.92 | I12: FALSE | J12: TRUE | K12: United States | L12: year | M12: 145000 | O12: CyberCoders | P12: ['python', 'azure', 'pytorch', 'tensorflow', 'opencv', 'datarobot']
A13: Data Engineer | B13: Systems & Data Engineer | C13: Boston, MA | D13: via LinkedIn | E13: Full-time | F13: FALSE | G13: Illinois, United States | H13: 44952.675 | I13: FALSE | J13: TRUE | K13: United States | L13: year | M13: 75000 | O13: New England Board of Higher Education | P13: ['sql', 'python', 'r', 'java', 'scala', 'aws', 'azure', 'tableau']
A14: Data Engineer | B14: Data Engineer | C14: Anywhere | D14: via LinkedIn | E14: Full-time | F14: TRUE | G14: Florida, United States | H14: 44944.634 | I14: TRUE | J14: FALSE | K14: United States | L14: year | M14: 105000 | O14: HirePlace | P14: ['no-sql', 'sql', 'python', 'scala', 'java', 'bash', 'powershell', 'azure', 'databricks', 'spark']
A15: Data Engineer | B15: Jr. Data Engineer | C15: Madison, WI | D15: via Ladders | E15: Full-time | F15: FALSE | G15: New York, United States | H15: 44935.087 | I15: FALSE | J15: FALSE | K15: United States | L15: year | M15: 90000 | O15: Baker Tilly | P15: ['sql', 'python', 'r', 'sql server', 'azure', 'databricks']
A16: Data Scientist | B16: Data Science Manager, Specialist Master - SFL Scientific | C16: San Jose, CA | D16: via Ladders | E16: Full-time | F16: FALSE | G16: California, United States | H16: 44946.515 | I16: FALSE | J16: FALSE | K16: United States | L16: year | M16: 200000 | O16: Deloitte | P16: ['python', 'aws', 'azure', 'gcp', 'keras', 'tensorflow', 'pytorch', 'pandas', 'scikit-learn', 'jupyter']
A17: Data Scientist | B17: Data Scientist I | C17: Boston, MA | D17: via ZipRecruiter | E17: Full-time | F17: FALSE | G17: New York, United States | H17: 44931.669 | I17: FALSE | J17: FALSE | K17: United States | L17: year | M17: 57500 | O17: Tresume and Asta CRS | P17: ['r', 'sql', 'python', 'scala', 'java', 'c++']
A18: Data Analyst | B18: Lead-Data Analyst | C18: St James, MO | D18: via My ArkLaMiss Jobs | E18: Full-time | F18: FALSE | G18: Illinois, United States | H18: 44928.751 | I18: FALSE | J18: TRUE | K18: United States | L18: year | M18: 144481.5 | O18: EDWARD JONES
A19: Data Scientist | B19: Data Science Instructor | C19: San Antonio, TX | D19: via LinkedIn | E19: Full-time | F19: FALSE | G19: Sudan | H19: 44936.752 | I19: FALSE | J19: TRUE | K19: Sudan | L19: year | M19: 77500 | O19: Codeup | P19: ['python', 'sql', 'matplotlib', 'seaborn', 'spark', 'hadoop', 'jupyter', 'tableau']
A20: Data Engineer | B20: Big Data Engineer | C20: Chicago, IL | D20: via LinkedIn | E20: Full-time | F20: FALSE | G20: Sudan | H20: 44952.328 | I20: FALSE | J20: FALSE | K20: Sudan | L20: year | M20: 105000 | O20: Robert Half | P20: ['python', 'sql', 'go', 'aws', 'databricks', 'spark', 'pyspark', 'airflow', 'alteryx', 'tableau']
A21: Data Analyst | B21: Institutional Credit Management - Lending Data Analyst - Vice... | C21: Pinellas Park, FL | D21: via ComputerWork | E21: Full-time | F21: FALSE | G21: Florida, United States | H21: 44951.669 | I21: FALSE | J21: FALSE | K21: United States | L21: year | M21: 132315 | O21: Citi | P21: ['cognos', 'tableau']
A22: Senior Data Scientist | B22: AI/ML - Senior Data Science Manager, AI/ML Data | C22: Cupertino, CA | D22: via My Champlain Valley Jobs | E22: Full-time | F22: FALSE | G22: California, United States | H22: 44938.754 | I22: FALSE | J22: TRUE | K22: United States | L22: year | M22: 173000 | O22: Apple
A23: Data Analyst | B23: Experian Data Analyst Remote / Telecommute Jobs | C23: Anywhere | D23: via Clearance Jobs | E23: Full-time | F23: TRUE | G23: New York, United States | H23: 44929.894 | I23: FALSE | J23: FALSE | K23: United States | L23: year | M23: 112500 | O23: Seneca Resources, LLC | P23: ['aws', 'linux']
A24: Data Scientist | B24: Electronics Data Scientist Intern | C24: Anywhere | D24: via Indeed | E24: Full-time | F24: TRUE | G24: California, United States | H24: 44953.379 | I24: FALSE | J24: FALSE | K24: United States | L24: hour | N24: 21.75 | O24: MilliporeSigma | P24: ['excel', 'outlook']
A25: Data Scientist | B25: Data Scientist (Genomics/Genetics, Python, AWS) - no c2c | C25: Anywhere | D25: via LinkedIn | E25: Contractor | F25: TRUE | G25: Texas, United States | H25: 44935.753 | I25: FALSE | J25: FALSE | K25: United States | L25: hour | N25: 66.5 | O25: neteffects | P25: ['python', 'r', 'sql', 'java', 'aws', 'gcp', 'airflow', 'docker', 'git', 'kubernetes']
A26: Senior Data Analyst | B26: Senior Data Analyst | C26: Ontario, CA | D26: via Indeed | E26: Full-time | F26: FALSE | G26: California, United States | H26: 44937.418 | I26: FALSE | J26: TRUE | K26: United States | L26: hour | N26: 34.875 | O26: Prime Healthcare Management Inc | P26: ['sql', 'excel']
A27: Data Analyst | B27: Data Analyst (Remote) | C27: Anywhere | D27: via Indeed | E27: Full-time | F27: TRUE | G27: Georgia | H27: 44940.405 | I27: FALSE | J27: FALSE | K27: United States | L27: year | M27: 52500 | O27: Acosta, Inc. | P27: ['windows', 'excel', 'word', 'powerpoint', 'power bi']
A28: Data Engineer | B28: Sr. Data Engineer | C28: Austin, TX | D28: via Indeed | E28: Full-time | F28: FALSE | G28: Georgia | H28: 44947.598 | I28: TRUE | J28: FALSE | K28: United States | L28: year | M28: 164500 | O28: Charles Schwab | P28: ['sql', 'python', 'java', 'gcp', 'bigquery', 'aws', 'vmware', 'pandas', 'spark', 'airflow', 'kafka', 'splunk', 'tableau', 'jira', 'confluence']
A29: Data Engineer | B29: Scientific Data Engineer (Remote Friendly) | C29: Anywhere | D29: via LinkedIn | E29: Full-time | F29: TRUE | G29: Texas, United States | H29: 44951.975 | I29: FALSE | J29: FALSE | K29: United States | L29: year | M29: 149874 | O29: Berkeley Lab | P29: ['python', 'java', 'javascript', 'bash', 'nosql', 'mysql', 'oracle', 'aws', 'linux']
A30: Data Analyst | B30: Lead Business Data Analyst - Global Delivery Services | C30: Santa Fe, NM | D30: via DirectlyApply | E30: Full-time | F30: FALSE | G30: Sudan | H30: 44932.163 | I30: TRUE | J30: FALSE | K30: Sudan | L30: year | M30: 115775 | O30: UKG (Ultimate Kronos Group) | P30: ['power bi', 'excel', 'tableau']
A31: Senior Data Analyst | B31: Senior Data Analyst - Cox Communities | C31: Oakton, VA | D31: via ZipRecruiter | E31: Full-time | F31: FALSE | G31: New York, United States | H31: 44930.417 | I31: FALSE | J31: TRUE | K31: United States | L31: year | M31: 96500 | O31: Cox Communications | P31: ['sql', 'alteryx', 'tableau']
A32: Senior Data Scientist | B32: Senior Data Scientist , Health Equity – Chicago, Boston, OR Remote | C32: Anywhere | D32: via Indeed | E32: Full-time | F32: TRUE | G32: Illinois, United States | H32: 44942.905 | I32: FALSE | J32: TRUE | K32: United States | L32: year | M32: 135000 | O32: CVS Health | P32: ['python', 'sql', 'gcp', 'azure', 'aws', 'hadoop']
A33: Data Scientist | B33: Manufacturing Data Scientist | C33: Englewood, CO | D33: via Indeed | E33: Full-time | F33: FALSE | G33: Sudan | H33: 44939.891 | I33: FALSE | J33: FALSE | K33: Sudan | L33: year | M33: 110000 | O33: Scytec Consulting Inc. | P33: ['sql', 'nosql', 'mongodb', 'mongodb', 'c#', 'sql server', 'azure', 'aws', 'git']
A34: Data Engineer | B34: Data Engineer | C34: New York, NY | D34: via LinkedIn | E34: Full-time | F34: FALSE | G34: Texas, United States | H34: 44950.632 | I34: FALSE | J34: FALSE | K34: United States | L34: year | M34: 155000 | O34: Revel IT | P34: ['sql', 'nosql', 'python', 'ruby', 'ruby', 'mysql', 'redshift', 'aws', 'tableau']
A35: Data Scientist | B35: Mathematics Statistician or Statistician (Data Scientist) 12 Month... | C35: Buffalo, NY | D35: via Buffalo, NY - Geebo | E35: Full-time | F35: FALSE | G35: Illinois, United States | H35: 44942.003 | I35: FALSE | J35: TRUE | K35: United States | L35: hour | N35: 24 | O35: Internal Revenue Service | P35: ['c', 'r', 'python', 'sql', 'java', 'oracle']
A36: Data Analyst | B36: Data Analyst | D36: via LinkedIn | E36: Full-time | F36: FALSE | G36: New York, United States | H36: 44929.686 | I36: TRUE | J36: FALSE | K36: United States | L36: year | M36: 97500 | O36: Robert Half | P36: ['sql', 't-sql', 'sql server', 'azure', 'ssrs', 'ssis']
A37: Data Engineer | B37: Data Engineer | C37: Washington, DC | D37: via PHL17 Jobs | E37: Full-time | F37: FALSE | G37: Georgia | H37: 44941.583 | I37: FALSE | J37: FALSE | K37: United States | L37: year | M37: 145000 | O37: Peraton | P37: ['python', 'sql', 'neo4j', 'mysql', 'aws', 'spark', 'express', 'splunk', 'git', 'jira', 'confluence']
A38: Data Engineer | B38: Data Engineer - A4370 | C38: Pleasanton, CA | D38: via Ai-Jobs.net | E38: Full-time | F38: FALSE | G38: California, United States | H38: 44937.839 | I38: FALSE | J38: TRUE | K38: United States | L38: year | M38: 147500 | O38: Nisum | P38: ['sql', 'spark']
A39: Senior Data Engineer | B39: Senior Data Engineer | C39: Woonsocket, RI | D39: via Indeed | E39: Full-time | F39: FALSE | G39: Illinois, United States | H39: 44933.921 | I39: FALSE | J39: TRUE | K39: United States | L39: year | M39: 135000 | O39: CVS Health | P39: ['sql', 'python', 'bash', 'oracle', 'snowflake', 'azure', 'gcp', 'hadoop']
A40: Senior Data Analyst | B40: Senior Data Analyst, Business Optimization | C40: Smyrna, GA | D40: via ZipRecruiter | E40: Full-time | F40: FALSE | G40: Georgia | H40: 44953.436 | I40: FALSE | J40: TRUE | K40: United States | L40: year | M40: 96500 | O40: Cox Communications | P40: ['swift', 'sql', 'excel', 'powerpoint', 'microstrategy', 'tableau']
A41: Data Engineer | B41: Data Engineer | C41: Malvern, PA | D41: via Dice | E41: Full-time | F41: FALSE | G41: Georgia | H41: 44935.863 | I41: TRUE | J41: FALSE | K41: United States | L41: year | M41: 70000 | O41: Acadia Technologies, Inc. | P41: ['pyspark']
A42: Senior Data Scientist | B42: Senior Data Scientist - ProServe | C42: Lakeland, FL | D42: via Lakeland, FL - Geebo | E42: Full-time | F42: FALSE | G42: Florida, United States | H42: 44929.983 | I42: FALSE | J42: FALSE | K42: United States | L42: hour | N42: 24 | O42: Amazon Web Services, Inc. | P42: ['aws', 'mxnet', 'tensorflow', 'pytorch', 'scikit-learn']
A43: Senior Data Analyst | B43: Senior Data Analyst | C43: New York, NY | D43: via LinkedIn | E43: Full-time | F43: FALSE | G43: New York, United States | H43: 44930.061 | I43: FALSE | J43: TRUE | K43: United States | L43: year | M43: 170000 | O43: Harnham | P43: ['sql', 'python', 'r', 'tableau', 'power bi', 'looker']
A44: Machine Learning Engineer | B44: Senior Machine Learning Engineer / Python Developer | C44: Lviv, Lviv Oblast, Ukraine | D44: via Ai-Jobs.net | E44: Full-time | F44: FALSE | G44: Ukraine | H44: 44945.193 | I44: FALSE | J44: FALSE | K44: Ukraine | L44: year | M44: 104668 | O44: LoopMe | P44: ['python', 'r', 'elasticsearch', 'airflow', 'spark', 'kafka']
A45: Data Engineer | B45: Cloud Data Engineer | C45: Broomfield, CO | D45: via LinkedIn | E45: Full-time | F45: FALSE | G45: Sudan | H45: 44951.916 | I45: FALSE | J45: TRUE | K45: Sudan | L45: year | M45: 125000 | O45: Noodles & Company | P45: ['python', 'sql', 'bigquery', 'gcp', 'power bi', 'git']
A46: Data Scientist | B46: Engineering Data Scientist, Ad Ranking | C46: New York, NY | D46: via Ladders | E46: Full-time | F46: FALSE | G46: New York, United States | H46: 44941.252 | I46: FALSE | J46: TRUE | K46: United States | L46: year | M46: 350000 | O46: Snap Inc | P46: ['sql', 'python', 'r', 'express']
A47: Machine Learning Engineer | B47: Senior AI Research Scientist | C47: Lisbon, Portugal | D47: via Ai-Jobs.net | E47: Full-time | F47: FALSE | G47: Portugal | H47: 44935.885 | I47: FALSE | J47: FALSE | K47: Portugal | L47: year | M47: 94342.5 | O47: Unbabel | P47: ['python', 'c++', 'pytorch', 'tensorflow']
A48: Data Engineer | B48: Lead Business Intelligence / Data Engineer: | C48: Brentwood, TN | D48: via LinkedIn | E48: Full-time | F48: FALSE | G48: Illinois, United States | H48: 44932.798 | I48: FALSE | J48: FALSE | K48: United States | L48: year | M48: 127500 | O48: Robert Half | P48: ['python', 'r', 't-sql', 'sql', 'go', 'oracle', 'jupyter', 'jquery', 'sharepoint', 'jenkins', 'docker', 'confluence']
A49: Data Scientist | B49: Staff Data Scientist | C49: Mountain View, CA | D49: via IT JobServe | E49: Full-time | F49: FALSE | G49: California, United States | H49: 44928.794 | I49: FALSE | J49: TRUE | K49: United States | L49: year | M49: 202500 | O49: CyberCoders | P49: ['python', 'java', 'scala', 'sql', 'aws', 'hadoop', 'spark', 'kafka', 'word']
A50: Data Engineer | B50: Quality Engineering Manager (Data) | C50: Waltham, MA | D50: via ZipRecruiter | E50: Full-time | F50: FALSE | G50: Sudan | H50: 44935.483 | I50: FALSE | J50: FALSE | K50: Sudan | L50: year | M50: 150000 | O50: National Grid (UK) | P50: ['sql', 'snowflake', 'power bi', 'ssrs']
A51: Senior Data Engineer | B51: Senior Data Engineer- Remote | C51: Frisco, TX | D51: via My ArkLaMiss Jobs | E51: Full-time | F51: FALSE | G51: Georgia | H51: 44938.39 | I51: FALSE | J51: TRUE | K51: United States | L51: year | M51: 138200 | O51: The Hartford | P51: ['python', 'aws', 'hadoop', 'spark']
A52: Data Analyst | B52: Sr Data Analyst | C52: Florham Park, NJ | D52: via LinkedIn | E52: Full-time | F52: FALSE | G52: New York, United States | H52: 44931.709 | I52: FALSE | J52: TRUE | K52: United States | L52: year | M52: 127500 | O52: Sompo International | P52: ['sql', 'sql server', 'db2', 'sap']
A53: Data Engineer | B53: Big Data Engineer | C53: Malvern, PA | D53: via LinkedIn | E53: Contractor | F53: FALSE | G53: Texas, United States | H53: 44956.798 | I53: FALSE | J53: FALSE | K53: United States | L53: hour | N53: 61.5 | O53: Robert Half | P53: ['sql', 'go', 'snowflake', 'ssis']
A54: Senior Data Engineer | B54: Senior Data Engineer- Uhaul Data ( Remote Eligible) | C54: Richmond, VA | D54: via WJTV Jobs | E54: Full-time | F54: FALSE | G54: New York, United States | H54: 44953.673 | I54: FALSE | J54: TRUE | K54: United States | L54: year | M54: 170672 | O54: Capital One | P54: ['java', 'scala', 'python', 'nosql', 'sql', 'mongo', 'shell', 'mysql', 'cassandra', 'redshift', 'snowflake', 'aws', 'azure', 'hadoop', 'kafka', 'spark']
A55: Data Engineer | B55: Data Engineer | C55: Springfield, VA | D55: via Ladders | E55: Full-time | F55: FALSE | G55: Florida, United States | H55: 44928.506 | I55: FALSE | J55: FALSE | K55: United States | L55: year | M55: 115000 | O55: National Geospatial-Intelligence Agency | P55: ['go', 'python', 'r', 'java', 'c', 'nosql', 'mongodb', 'mongodb', 'elasticsearch', 'mysql', 'postgresql', 'neo4j', 'oracle', 'aws', 'sap', 'terraform', 'ansible']
A56: Senior Data Engineer | B56: Senior Data Engineer ETL/Oracle | C56: Denver, CO | D56: via Ladders | E56: Full-time | F56: FALSE | G56: Illinois, United States | H56: 44953.3 | I56: FALSE | J56: TRUE | K56: United States | L56: year | M56: 150000 | O56: TIAA | P56: ['shell', 'java', 'oracle', 'snowflake', 'unix', 'splunk', 'flow', 'git']
A57: Data Scientist | B57: VP, Data Science | C57: United States | D57: via My ArkLaMiss Jobs | E57: Full-time | F57: FALSE | G57: Sudan | H57: 44946.081 | I57: FALSE | J57: FALSE | K57: Sudan | L57: year | M57: 265500 | O57: MediaMath | P57: ['python', 'scala', 'spark']
A58: Data Engineer | B58: Staff / Principal Data Engineer | C58: Anywhere | D58: via LinkedIn | E58: Full-time | F58: TRUE | G58: Georgia | H58: 44951.569 | I58: FALSE | J58: TRUE | K58: United States | L58: year | M58: 155000 | O58: Prestige Staffing | P58: ['sql', 'azure', 'puppet', 'terraform', 'jenkins']
A59: Data Engineer | B59: Principal Data Engineer | C59: Arlington Heights, IL | D59: via Dice | E59: Full-time | F59: FALSE | G59: Illinois, United States | H59: 44936.048 | I59: FALSE | J59: TRUE | K59: United States | L59: year | M59: 145000 | O59: Jobot | P59: ['scala', 'java', 'python', 'cassandra', 'databricks', 'azure', 'aws', 'spark', 'kafka', 'kubernetes', 'docker']
A60: Data Scientist | B60: Data Scientist II | C60: California | D60: via Farmers District Office - Talentify | E60: Full-time | F60: FALSE | G60: California, United States | H60: 44944.001 | I60: FALSE | J60: TRUE | K60: United States | L60: year | M60: 135000 | O60: Farmers Insurance | P60: ['sql', 'python', 'c++', 'ssis', 'tableau']
A61: Senior Data Engineer | B61: AWS Senior Cloud Data Engineer | C61: Anywhere | D61: via Upwork | E61: Contractor | F61: TRUE | G61: California, United States | H61: 44936.35 | I61: TRUE | J61: FALSE | K61: United States | L61: hour | N61: 16.5 | O61: Upwork | P61: ['aws', 'redshift', 'git']
A62: Data Analyst | B62: Data Capabilities Analyst | C62: Irving, TX | D62: via Ladders | E62: Full-time | F62: FALSE | G62: Texas, United States | H62: 44930.437 | I62: FALSE | J62: FALSE | K62: United States | L62: year | M62: 115000 | O62: Citigroup, Inc | P62: ['excel', 'powerpoint']
A63: Data Engineer | B63: Senior Data Engineer II | C63: Los Angeles, CA | D63: via Ladders | E63: Full-time | F63: FALSE | G63: Illinois, United States | H63: 44931.354 | I63: TRUE | J63: FALSE | K63: United States | L63: year | M63: 90000 | O63: McKinsey & Company | P63: ['python', 'sql', 'databricks', 'snowflake', 'aws', 'gcp', 'azure', 'pyspark', 'airflow', 'kafka', 'docker', 'kubernetes']
A64: Senior Data Analyst | B64: Senior Game Data Analyst - Tarboosh Studio | C64: Paris, France | D64: via Ai-Jobs.net | E64: Full-time | F64: FALSE | G64: France | H64: 44949.925 | I64: TRUE | J64: FALSE | K64: France | L64: year | M64: 111175 | O64: Voodoo | P64: ['sql', 'r', 'python']
A65: Senior Data Engineer | B65: Senior Data Engineer | C65: DeSoto, TX | D65: via Ladders | E65: Full-time | F65: FALSE | G65: Georgia | H65: 44930.442 | I65: FALSE | J65: TRUE | K65: United States | L65: year | M65: 150000 | O65: Caterpillar, Inc | P65: ['sql', 'nosql', 'python', 'ruby', 'ruby', 'java']
A66: Data Engineer | B66: ERP Data Engineer | C66: Lansing, MI | D66: via LinkedIn | E66: Full-time | F66: FALSE | G66: Sudan | H66: 44936.71 | I66: FALSE | J66: FALSE | K66: Sudan | L66: year | M66: 80000 | O66: Venteon | P66: ['sql', 'sap']
A67: Data Scientist | B67: Head of Data Science | C67: Anywhere | D67: via LinkedIn | E67: Full-time | F67: TRUE | G67: Sudan | H67: 44930.581 | I67: FALSE | J67: TRUE | K67: Sudan | L67: year | M67: 215000 | O67: Lawrence Harvey
A68: Senior Data Analyst | B68: Sr Data Analyst | $90k | Lake Forest, IL | C68: Lake Forest, IL | D68: via Recruit.net | E68: Full-time | F68: FALSE | G68: Illinois, United States | H68: 44949.002 | I68: TRUE | J68: FALSE | K68: United States | L68: year | M68: 90000 | O68: Trinity Intl.
A69: Data Analyst | B69: SQL Developer/Data Analyst | C69: New York, NY | D69: via Dice | E69: Contractor | F69: FALSE | G69: New York, United States | H69: 44956.542 | I69: FALSE | J69: FALSE | K69: United States | L69: hour | N69: 60 | O69: Infosight Consulting Inc | P69: ['sql', 'python', 'sql server', 'oracle']
A70: Data Scientist | B70: Data Analyst / Data Scientist | C70: Anywhere | D70: via Y Combinator | E70: Full-time | F70: TRUE | G70: California, United States | H70: 44946.723 | I70: FALSE | J70: TRUE | K70: United States | L70: year | M70: 160000 | O70: Y Combinator | P70: ['sql', 'python']
A71: Data Analyst | B71: Data Analyst with FinTech- | C71: Austin, TX | D71: via Austin, TX - Geebo | E71: Full-time | F71: FALSE | G71: Texas, United States | H71: 44942.001 | I71: TRUE | J71: FALSE | K71: United States | L71: hour | N71: 24 | O71: EXPERIS | P71: ['sql', 'snowflake']
A72: Senior Data Scientist | B72: Senior Data Scientist | C72: Austin, TX | D72: via LinkedIn | E72: Full-time | F72: FALSE | G72: Texas, United States | H72: 44937.962 | I72: FALSE | J72: TRUE | K72: United States | L72: year | M72: 160000 | O72: Primis | P72: ['python', 'sql', 'tableau']
A73: Senior Data Engineer | B73: Senior IT Data Engineer | C73: Fort Meade, MD | D73: via Ladders | E73: Full-time | F73: FALSE | G73: Georgia | H73: 44948.418 | I73: FALSE | J73: TRUE | K73: United States | L73: year | M73: 150000 | O73: Leidos | P73: ['python', 'java', 'kafka', 'linux', 'ansible', 'flow']
A74: Senior Data Engineer | B74: Senior Data Engineer | C74: San Diego, CA | D74: via LinkedIn | E74: Full-time | F74: FALSE | G74: Illinois, United States | H74: 44932.715 | I74: FALSE | J74: TRUE | K74: United States | L74: year | M74: 140000 | O74: Robert Half | P74: ['python', 'sql', 'nosql', 'azure', 'oracle', 'databricks', 'phoenix']
A75: Data Engineer | B75: Data Engineer | C75: Anywhere | D75: via Robert Half | E75: Full-time | F75: TRUE | G75: New York, United States | H75: 44935.588 | I75: TRUE | J75: FALSE | K75: United States | L75: year | M75: 140000 | O75: Robert Half | P75: ['python', 'sql', 'java', 't-sql', 'oracle', 'spark', 'pyspark', 'kafka', 'airflow', 'linux', 'sap', 'github']
A76: Senior Data Scientist | B76: Senior Data Scientist | C76: Foster City, CA | D76: via Ai-Jobs.net | E76: Full-time | F76: FALSE | G76: California, United States | H76: 44932.253 | I76: FALSE | J76: TRUE | K76: United States | L76: year | M76: 161000 | O76: Visa | P76: ['python', 'r', 'sql', 'spark', 'jupyter', 'word', 'excel', 'powerpoint']
A77: Data Engineer | B77: Data Engineer | C77: Anywhere | D77: via Indeed | E77: Full-time | F77: TRUE | G77: California, United States | H77: 44957.671 | I77: FALSE | J77: FALSE | K77: United States | L77: year | M77: 85000 | O77: DBSI Services | P77: ['sql', 'visual basic', 'oracle']
A78: Data Analyst | B78: Data Analyst | C78: McLean, VA | D78: via LinkedIn | E78: Contractor | F78: FALSE | G78: New York, United States | H78: 44937.667 | I78: TRUE | J78: FALSE | K78: United States | L78: hour | N78: 40 | O78: Mindlance | P78: ['python', 'sql', 'postgresql', 'aws', 'tableau']
A79: Data Engineer | B79: Data Engineer | C79: Anywhere | D79: via LinkedIn | E79: Full-time | F79: TRUE | G79: Canada | H79: 44950.01 | I79: FALSE | J79: FALSE | K79: Canada | L79: year | M79: 124000 | O79: GRIN | P79: ['python', 'sql', 'no-sql', 'bigquery', 'snowflake', 'airflow', 'kafka', 'spark']
A80: Data Scientist | B80: Mathematical Statistician (Data Scientist) or Statistician (Data... | C80: Charlotte, NC | D80: via DiversityJobs | E80: Full-time | F80: FALSE | G80: Illinois, United States | H80: 44937.379 | I80: FALSE | J80: TRUE | K80: United States | L80: year | M80: 143910.5 | O80: Internal Revenue Service | P80: ['c']
A81: Data Scientist | B81: Jr. Data Scientist | C81: Anywhere | D81: via LinkedIn | E81: Full-time | F81: TRUE | G81: Texas, United States | H81: 44939.921 | I81: FALSE | J81: FALSE | K81: United States | L81: year | M81: 75000 | O81: Take2 Consulting, LLC | P81: ['python', 'r', 'aws', 'gcp', 'tableau', 'git', 'github', 'jenkins', 'jira']
A82: Senior Data Engineer | B82: Senior Data Engineer | C82: Anywhere | D82: via LinkedIn | E82: Full-time | F82: TRUE | G82: Florida, United States | H82: 44939.591 | I82: FALSE | J82: FALSE | K82: United States | L82: year | M82: 150000 | O82: Alldus | P82: ['python', 'aws']
A83: Senior Data Scientist | B83: Senior Data Scientist | C83: Dayton, OH | D83: via Indeed | E83: Full-time | F83: FALSE | G83: Illinois, United States | H83: 44932.587 | I83: FALSE | J83: TRUE | K83: United States | L83: year | M83: 140000 | O83: Illumination Works | P83: ['python', 'mongodb', 'mongodb', 'neo4j', 'databricks', 'snowflake', 'azure', 'aws', 'pandas', 'numpy', 'scikit-learn', 'pytorch', 'tensorflow', 'keras', 'pyspark', 'hadoop', 'git']
A84: Data Engineer | B84: Azure Data Engineer / Datawarehouse Consultant | C84: Anywhere | D84: via LinkedIn | E84: Full-time | F84: TRUE | G84: New York, United States | H84: 44930.88 | I84: FALSE | J84: FALSE | K84: United States | L84: hour | N84: 85 | O84: Medix Technology | P84: ['sql', 'azure', 'oracle', 'databricks', 'ssis']
A85: Data Scientist | B85: Data Scientist, CX Strategy and Enablement (Austin, TX) | C85: Austin, TX | D85: via Built In Austin | E85: Full-time | F85: FALSE | G85: Sudan | H85: 44937.451 | I85: FALSE | J85: TRUE | K85: Sudan | L85: year | M85: 137110 | O85: LogicMonitor | P85: ['python', 'r', 'scala', 'looker', 'excel']
A86: Data Engineer | B86: Data Engineer | C86: California | D86: via LinkedIn | E86: Full-time | F86: FALSE | G86: California, United States | H86: 44957.588 | I86: FALSE | J86: FALSE | K86: United States | L86: year | M86: 110000 | O86: Northbound Executive Search | P86: ['python', 'java', 'sql', 'azure', 'snowflake', 'databricks']
A87: Senior Data Scientist | B87: Data Scientist/Senior Data Scientist | C87: Anywhere | D87: via LinkedIn | E87: Full-time | F87: TRUE | G87: Sudan | H87: 44936.71 | I87: FALSE | J87: FALSE | K87: Sudan | L87: year | M87: 165000 | O87: Harnham | P87: ['python', 'sql', 'git']
A88: Data Engineer | B88: Lead Data Engineer | C88: Anywhere | D88: via LinkedIn | E88: Full-time | F88: TRUE | G88: Illinois, United States | H88: 44952.925 | I88: FALSE | J88: TRUE | K88: United States | L88: year | M88: 165000 | O88: Intelletec | P88: ['python', 'sql', 'redshift', 'aws']
A89: Data Engineer | B89: Data engineer | C89: Anywhere | D89: via Upwork | E89: Contractor | F89: TRUE | G89: California, United States | H89: 44932.186 | I89: TRUE | J89: FALSE | K89: United States | L89: hour | N89: 60 | O89: Upwork | P89: ['python']
A90: Data Engineer | B90: Data Engineer - Mid Level | C90: Weston, TX | D90: via WREG Jobs | E90: Full-time | F90: FALSE | G90: Florida, United States | H90: 44928.631 | I90: FALSE | J90: TRUE | K90: United States | L90: year | M90: 123600 | O90: USAA | P90: ['sql', 'python', 'snowflake', 'phoenix']
A91: Data Scientist | B91: Working Student in Data Science for (e-)Mobility Cloud Solutions... | C91: Cluj-Napoca, Romania | D91: via Ai-Jobs.net | E91: Full-time | F91: FALSE | G91: Romania | H91: 44953.715 | I91: FALSE | J91: FALSE | K91: Romania | L91: year | M91: 56700 | O91: Bosch Group | P91: ['python', 'mongo', 'sql', 'azure', 'spark', 'hadoop', 'pandas', 'numpy', 'seaborn', 'docker', 'git']
A92: Data Engineer | B92: Data Engineer | C92: Zürich, Switzerland | D92: via Ai-Jobs.net | E92: Full-time | F92: FALSE | G92: Switzerland | H92: 44937.245 | I92: FALSE | J92: FALSE | K92: Switzerland | L92: year | M92: 147500 | O92: Capco | P92: ['python', 'shell', 'aws', 'kafka', 'pyspark', 'hadoop', 'spark', 'django', 'tableau', 'jenkins', 'ansible', 'chef', 'kubernetes', 'docker']
A93: Data Analyst | B93: Data Analyst | C93: Bethesda, MD | D93: via Ladders | E93: Full-time | F93: FALSE | G93: New York, United States | H93: 44942.386 | I93: FALSE | J93: FALSE | K93: United States | L93: year | M93: 175000 | O93: Xator Corp | P93: ['sql', 'r', 'python', 'excel', 'tableau', 'ms access']
A94: Data Scientist | B94: SAS Data Scientist | C94: Anywhere | D94: via Indeed | E94: Full-time | F94: TRUE | G94: Sudan | H94: 44939.099 | I94: FALSE | J94: TRUE | K94: Sudan | L94: year | M94: 99790 | O94: Tista Science and Technology Corporation | P94: ['vba', 'sas', 'sas', 'r', 'sql', 'db2', 'sql server', 'windows', 'unix']
A95: Data Scientist | B95: Lead Data Scientist, Gas Load Forecasting, Load Forecasting ... | C95: Hicksville, NY | D95: via KHON2 Jobs | E95: Full-time | F95: FALSE | G95: New York, United States | H95: 44940.752 | I95: FALSE | J95: FALSE | K95: United States | L95: year | M95: 128500 | O95: NATIONAL GRID CO USA (NE POWER) | P95: ['r', 'python', 'sql', 'excel']
A96: Data Scientist | B96: Data Scientist, Analytics - Trust & Safety | C96: San Jose, CA | D96: via LinkedIn | E96: Full-time | F96: FALSE | G96: California, United States | H96: 44953.462 | I96: FALSE | J96: TRUE | K96: United States | L96: year | M96: 209955.5 | O96: TikTok | P96: ['sql']
A97: Data Analyst | B97: Data Management Governance Analyst | C97: Hawaiian Gardens, CA | D97: via Ladders | E97: Full-time | F97: FALSE | G97: California, United States | H97: 44931.459 | I97: FALSE | J97: FALSE | K97: United States | L97: year | M97: 115000 | O97: NTT DATA Services | P97: ['sql', 'r', 'python', 'oracle', 'tableau', 'power bi', 'alteryx', 'flow']
A98: Data Analyst | B98: Senior, Data Analyst (Channel Analytics) | C98: Seoul, South Korea | D98: via Ai-Jobs.net | E98: Full-time | F98: FALSE | G98: South Korea | H98: 44944.734 | I98: FALSE | J98: FALSE | K98: South Korea | L98: year | M98: 111175 | O98: Coupang | P98: ['r', 'python', 'airflow', 'tableau', 'github', 'jira', 'confluence']
A99: Data Engineer | B99: Lead Data Engineer | C99: Floral Park, NY | D99: via KHON2 Jobs | E99: Full-time | F99: FALSE | G99: Illinois, United States | H99: 44953.675 | I99: FALSE | J99: TRUE | K99: United States | L99: year | M99: 208114 | O99: Capital One | P99: ['java', 'scala', 'python', 'nosql', 'sql', 'mongo', 'shell', 'mysql', 'cassandra', 'redshift', 'snowflake', 'aws', 'azure', 'hadoop', 'kafka', 'spark']
A100: Data Analyst | B100: Market Data Analyst f/m | C100: Egypt | D100: via Ai-Jobs.net | E100: Full-time | F100: FALSE | G100: Egypt | H100: 44945.306 | I100: FALSE | J100: FALSE | K100: Egypt | L100: year | M100: 51014 | O100: Bosch Group | P100: ['r', 'sql', 'python', 'spark', 'tableau', 'excel']
...

Sheet Skills Analysis
A1: Skills Demand Analysis — Data Job Postings, January 2023
A2: Source: 'Jan - Copy & Paste' (columns A, M, P). All figures are formula-driven.
A4: Dataset summary
A5: Total job postings | B5: =COUNTA('Jan - Copy & Paste'!$A$2:$A$3103) -> 3102
A6: Postings with skills listed | B6: =COUNTIF('Jan - Copy & Paste'!$P$2:$P$3103,"*'*") -> 2821
A7: Postings with annual salary | B7: =COUNTIF('Jan - Copy & Paste'!$M$2:$M$3103,">0") -> 2287
A8: Overall avg annual salary | B8: =AVERAGEIF('Jan - Copy & Paste'!$M$2:$M$3103,">0") -> 123064.16
A9: Distinct skills in dataset | B9: 179
A11: Rank | B11: Skill | C11: Postings | D11: % of skilled postings | E11: Avg salary ($/yr) | F11: vs overall avg | G11: Salary sample (n)
A12: =RANK(C12,$C$12:$C$36) -> 1 | B12: sql | C12: =COUNTIF('Jan - Copy & Paste'!$P$2:$P$3103,"*'"&$B12&"'*") -> 1793 | D12: =C12/$B$6 -> 0.63559022 | E12: =AVERAGEIFS('Jan - Copy & Paste'!$M$2:$M$3103,'Jan - Copy & Paste'!$P$2:$P$3103,"*'"&$B12&"'*",'Jan - Copy & Paste'!$M$2:$M$3103,">0") -> 125281.34 | F12: =E12/$B$8-1 -> 0.018016437 | G12: =COUNTIFS('Jan - Copy & Paste'!$P$2:$P$3103,"*'"&$B12&"'*",'Jan - Copy & Paste'!$M$2:$M$3103,">0") -> 1344
A13: =RANK(C13,$C$12:$C$36) -> 2 | B13: python | C13: =COUNTIF('Jan - Copy & Paste'!$P$2:$P$3103,"*'"&$B13&"'*") -> 1657 | D13: =C13/$B$6 -> 0.58738036 | E13: =AVERAGEIFS('Jan - Copy & Paste'!$M$2:$M$3103,'Jan - Copy & Paste'!$P$2:$P$3103,"*'"&$B13&"'*",'Jan - Copy & Paste'!$M$2:$M$3103,">0") -> 132378.18 | F13: =E13/$B$8-1 -> 0.075684247 | G13: =COUNTIFS('Jan - Copy & Paste'!$P$2:$P$3103,"*'"&$B13&"'*",'Jan - Copy & Paste'!$M$2:$M$3103,">0") -> 1338
A14: =RANK(C14,$C$12:$C$36) -> 3 | B14: r | C14: =COUNTIF('Jan - Copy & Paste'!$P$2:$P$3103,"*'"&$B14&"'*") -> 710 | D14: =C14/$B$6 -> 0.2516838 | E14: =AVERAGEIFS('Jan - Copy & Paste'!$M$2:$M$3103,'Jan - Copy & Paste'!$P$2:$P$3103,"*'"&$B14&"'*",'Jan - Copy & Paste'!$M$2:$M$3103,">0") -> 128126.73 | F14: =E14/$B$8-1 -> 0.041137669 | G14: =COUNTIFS('Jan - Copy & Paste'!$P$2:$P$3103,"*'"&$B14&"'*",'Jan - Copy & Paste'!$M$2:$M$3103,">0") -> 559
A15: =RANK(C15,$C$12:$C$36) -> 4 | B15: tableau | C15: =COUNTIF('Jan - Copy & Paste'!$P$2:$P$3103,"*'"&$B15&"'*") -> 650 | D15: =C15/$B$6 -> 0.23041475 | E15: =AVERAGEIFS('Jan - Copy & Paste'!$M$2:$M$3103,'Jan - Copy & Paste'!$P$2:$P$3103,"*'"&$B15&"'*",'Jan - Copy & Paste'!$M$2:$M$3103,">0") -> 114357.86 | F15: =E15/$B$8-1 -> -0.070746 | G15: =COUNTIFS('Jan - Copy & Paste'!$P$2:$P$3103,"*'"&$B15&"'*",'Jan - Copy & Paste'!$M$2:$M$3103,">0") -> 497
A16: =RANK(C16,$C$12:$C$36) -> 5 | B16: excel | C16: =COUNTIF('Jan - Copy & Paste'!$P$2:$P$3103,"*'"&$B16&"'*") -> 646 | D16: =C16/$B$6 -> 0.22899681 | E16: =AVERAGEIFS('Jan - Copy & Paste'!$M$2:$M$3103,'Jan - Copy & Paste'!$P$2:$P$3103,"*'"&$B16&"'*",'Jan - Copy & Paste'!$M$2:$M$3103,">0") -> 99670.414 | F16: =E16/$B$8-1 -> -0.19009391 | G16: =COUNTIFS('Jan - Copy & Paste'!$P$2:$P$3103,"*'"&$B16&"'*",'Jan - Copy & Paste'!$M$2:$M$3103,">0") -> 419
A17: =RANK(C17,$C$12:$C$36) -> 6 | B17: aws | C17: =COUNTIF('Jan - Copy & Paste'!$P$2:$P$3103,"*'"&$B17&"'*") -> 594 | D17: =C17/$B$6 -> 0.21056363 | E17: =AVERAGEIFS('Jan - Copy & Paste'!$M$2:$M$3103,'Jan - Copy & Paste'!$P$2:$P$3103,"*'"&$B17&"'*",'Jan - Copy & Paste'!$M$2:$M$3103,">0") -> 137935.96 | F17: =E17/$B$8-1 -> 0.12084589 | G17: =COUNTIFS('Jan - Copy & Paste'!$P$2:$P$3103,"*'"&$B17&"'*",'Jan - Copy & Paste'!$M$2:$M$3103,">0") -> 480
A18: =RANK(C18,$C$12:$C$36) -> 7 | B18: spark | C18: =COUNTIF('Jan - Copy & Paste'!$P$2:$P$3103,"*'"&$B18&"'*") -> 498 | D18: =C18/$B$6 -> 0.17653314 | E18: =AVERAGEIFS('Jan - Copy & Paste'!$M$2:$M$3103,'Jan - Copy & Paste'!$P$2:$P$3103,"*'"&$B18&"'*",'Jan - Copy & Paste'!$M$2:$M$3103,">0") -> 141550.54 | F18: =E18/$B$8-1 -> 0.15021738 | G18: =COUNTIFS('Jan - Copy & Paste'!$P$2:$P$3103,"*'"&$B18&"'*",'Jan - Copy & Paste'!$M$2:$M$3103,">0") -> 426
A19: =RANK(C19,$C$12:$C$36) -> 8 | B19: azure | C19: =COUNTIF('Jan - Copy & Paste'!$P$2:$P$3103,"*'"&$B19&"'*") -> 414 | D19: =C19/$B$6 -> 0.14675647 | E19: =AVERAGEIFS('Jan - Copy & Paste'!$M$2:$M$3103,'Jan - Copy & Paste'!$P$2:$P$3103,"*'"&$B19&"'*",'Jan - Copy & Paste'!$M$2:$M$3103,">0") -> 130034.88 | F19: =E19/$B$8-1 -> 0.056642932 | G19: =COUNTIFS('Jan - Copy & Paste'!$P$2:$P$3103,"*'"&$B19&"'*",'Jan - Copy & Paste'!$M$2:$M$3103,">0") -> 343
A20: =RANK(C20,$C$12:$C$36) -> 9 | B20: java | C20: =COUNTIF('Jan - Copy & Paste'!$P$2:$P$3103,"*'"&$B20&"'*") -> 328 | D20: =C20/$B$6 -> 0.11627083 | E20: =AVERAGEIFS('Jan - Copy & Paste'!$M$2:$M$3103,'Jan - Copy & Paste'!$P$2:$P$3103,"*'"&$B20&"'*",'Jan - Copy & Paste'!$M$2:$M$3103,">0") -> 131235.19 | F20: =E20/$B$8-1 -> 0.066396516 | G20: =COUNTIFS('Jan - Copy & Paste'!$P$2:$P$3103,"*'"&$B20&"'*",'Jan - Copy & Paste'!$M$2:$M$3103,">0") -> 283
A21: =RANK(C21,$C$12:$C$36) -> 10 | B21: power bi | C21: =COUNTIF('Jan - Copy & Paste'!$P$2:$P$3103,"*'"&$B21&"'*") -> 324 | D21: =C21/$B$6 -> 0.11485289 | E21: =AVERAGEIFS('Jan - Copy & Paste'!$M$2:$M$3103,'Jan - Copy & Paste'!$P$2:$P$3103,"*'"&$B21&"'*",'Jan - Copy & Paste'!$M$2:$M$3103,">0") -> 104707.91 | F21: =E21/$B$8-1 -> -0.14916004 | G21: =COUNTIFS('Jan - Copy & Paste'!$P$2:$P$3103,"*'"&$B21&"'*",'Jan - Copy & Paste'!$M$2:$M$3103,">0") -> 252
A22: =RANK(C22,$C$12:$C$36) -> 11 | B22: hadoop | C22: =COUNTIF('Jan - Copy & Paste'!$P$2:$P$3103,"*'"&$B22&"'*") -> 291 | D22: =C22/$B$6 -> 0.10315491 | E22: =AVERAGEIFS('Jan - Copy & Paste'!$M$2:$M$3103,'Jan - Copy & Paste'!$P$2:$P$3103,"*'"&$B22&"'*",'Jan - Copy & Paste'!$M$2:$M$3103,">0") -> 141100.97 | F22: =E22/$B$8-1 -> 0.14656426 | G22: =COUNTIFS('Jan - Copy & Paste'!$P$2:$P$3103,"*'"&$B22&"'*",'Jan - Copy & Paste'!$M$2:$M$3103,">0") -> 242
A23: =RANK(C23,$C$12:$C$36) -> 12 | B23: snowflake | C23: =COUNTIF('Jan - Copy & Paste'!$P$2:$P$3103,"*'"&$B23&"'*") -> 281 | D23: =C23/$B$6 -> 0.099610067 | E23: =AVERAGEIFS('Jan - Copy & Paste'!$M$2:$M$3103,'Jan - Copy & Paste'!$P$2:$P$3103,"*'"&$B23&"'*",'Jan - Copy & Paste'!$M$2:$M$3103,">0") -> 137522.69 | F23: =E23/$B$8-1 -> 0.11748768 | G23: =COUNTIFS('Jan - Copy & Paste'!$P$2:$P$3103,"*'"&$B23&"'*",'Jan - Copy & Paste'!$M$2:$M$3103,">0") -> 233
... A36: =RANK(C36,$C$12:$C$36) -> 25 | B36: databricks | C36: =COUNTIF('Jan - Copy & Paste'!$P$2:$P$3103,"*'"&$B36&"'*") -> 166 | D36: =C36/$B$6 -> 0.058844381 | E36: =AVERAGEIFS('Jan - Copy & Paste'!$M$2:$M$3103,'Jan - Copy & Paste'!$P$2:$P$3103,"*'"&$B36&"'*",'Jan - Copy & Paste'!$M$2:$M$3103,">0") -> 133015.12 | F36: =E36/$B$8-1 -> 0.080859921 | G36: =COUNTIFS('Jan - Copy & Paste'!$P$2:$P$3103,"*'"&$B36&"'*",'Jan - Copy & Paste'!$M$2:$M$3103,">0") -> 124
A39: Top skills by role — % of that role's postings mentioning the skill
B41: Skill | C41: Data Analyst | D41: Data Scientist | E41: Data Engineer | F41: Senior Data Analyst | G41: Senior Data Scientist | H41: Senior Data Engineer | I41: Machine Learning Engineer
B42: Postings in role | C42: =COUNTIF('Jan - Copy & Paste'!$A$2:$A$3103,C$41) -> 982 | D42: =COUNTIF('Jan - Copy & Paste'!$A$2:$A$3103,D$41) -> 869 | E42: =COUNTIF('Jan - Copy & Paste'!$A$2:$A$3103,E$41) -> 522 | F42: =COUNTIF('Jan - Copy & Paste'!$A$2:$A$3103,F$41) -> 191 | G42: =COUNTIF('Jan - Copy & Paste'!$A$2:$A$3103,G$41) -> 236 | H42: =COUNTIF('Jan - Copy & Paste'!$A$2:$A$3103,H$41) -> 145 | I42: =COUNTIF('Jan - Copy & Paste'!$A$2:$A$3103,I$41) -> 74
B43: sql | C43: =COUNTIFS('Jan - Copy & Paste'!$A$2:$A$3103,C$41,'Jan - Copy & Paste'!$P$2:$P$3103,"*'"&$B43&"'*")/C$42 -> 0.53869654 | D43: =COUNTIFS('Jan - Copy & Paste'!$A$2:$A$3103,D$41,'Jan - Copy & Paste'!$P$2:$P$3103,"*'"&$B43&"'*")/D$42 -> 0.54890679 | E43: =COUNTIFS('Jan - Copy & Paste'!$A$2:$A$3103,E$41,'Jan - Copy & Paste'!$P$2:$P$3103,"*'"&$B43&"'*")/E$42 -> 0.66858238 | F43: =COUNTIFS('Jan - Copy & Paste'!$A$2:$A$3103,F$41,'Jan - Copy & Paste'!$P$2:$P$3103,"*'"&$B43&"'*")/F$42 -> 0.7382199 | G43: =COUNTIFS('Jan - Copy & Paste'!$A$2:$A$3103,G$41,'Jan - Copy & Paste'!$P$2:$P$3103,"*'"&$B43&"'*")/G$42 -> 0.61440678 | H43: =COUNTIFS('Jan - Copy & Paste'!$A$2:$A$3103,H$41,'Jan - Copy & Paste'!$P$2:$P$3103,"*'"&$B43&"'*")/H$42 -> 0.69655172 | I43: =COUNTIFS('Jan - Copy & Paste'!$A$2:$A$3103,I$41,'Jan - Copy & Paste'!$P$2:$P$3103,"*'"&$B43&"'*")/I$42 -> 0.22972973
B44: python | C44: =COUNTIFS('Jan - Copy & Paste'!$A$2:$A$3103,C$41,'Jan - Copy & Paste'!$P$2:$P$3103,"*'"&$B44&"'*")/C$42 -> 0.27494908 | D44: =COUNTIFS('Jan - Copy & Paste'!$A$2:$A$3103,D$41,'Jan - Copy & Paste'!$P$2:$P$3103,"*'"&$B44&"'*")/D$42 -> 0.72036824 | E44: =COUNTIFS('Jan - Copy & Paste'!$A$2:$A$3103,E$41,'Jan - Copy & Paste'!$P$2:$P$3103,"*'"&$B44&"'*")/E$42 -> 0.63793103 | F44: =COUNTIFS('Jan - Copy & Paste'!$A$2:$A$3103,F$41,'Jan - Copy & Paste'!$P$2:$P$3103,"*'"&$B44&"'*")/F$42 -> 0.39790576 | G44: =COUNTIFS('Jan - Copy & Paste'!$A$2:$A$3103,G$41,'Jan - Copy & Paste'!$P$2:$P$3103,"*'"&$B44&"'*")/G$42 -> 0.73728814 | H44: =COUNTIFS('Jan - Copy & Paste'!$A$2:$A$3103,H$41,'Jan - Copy & Paste'!$P$2:$P$3103,"*'"&$B44&"'*")/H$42 -> 0.73793103 | I44: =COUNTIFS('Jan - Copy & Paste'!$A$2:$A$3103,I$41,'Jan - Copy & Paste'!$P$2:$P$3103,"*'"&$B44&"'*")/I$42 -> 0.62162162
B45: r | C45: =COUNTIFS('Jan - Copy & Paste'!$A$2:$A$3103,C$41,'Jan - Copy & Paste'!$P$2:$P$3103,"*'"&$B45&"'*")/C$42 -> 0.1598778 | D45: =COUNTIFS('Jan - Copy & Paste'!$A$2:$A$3103,D$41,'Jan - Copy & Paste'!$P$2:$P$3103,"*'"&$B45&"'*")/D$42 -> 0.40391254 | E45: =COUNTIFS('Jan - Copy & Paste'!$A$2:$A$3103,E$41,'Jan - Copy & Paste'!$P$2:$P$3103,"*'"&$B45&"'*")/E$42 -> 0.063218391 | F45: =COUNTIFS('Jan - Copy & Paste'!$A$2:$A$3103,F$41,'Jan - Copy & Paste'!$P$2:$P$3103,"*'"&$B45&"'*")/F$42 -> 0.27225131 | G45: =COUNTIFS('Jan - Copy & Paste'!$A$2:$A$3103,G$41,'Jan - Copy & Paste'!$P$2:$P$3103,"*'"&$B45&"'*")/G$42 -> 0.41101695 | H45: =COUNTIFS('Jan - Copy & Paste'!$A$2:$A$3103,H$41,'Jan - Copy & Paste'!$P$2:$P$3103,"*'"&$B45&"'*")/H$42 -> 0.027586207 | I45: =COUNTIFS('Jan - Copy & Paste'!$A$2:$A$3103,I$41,'Jan - Copy & Paste'!$P$2:$P$3103,"*'"&$B45&"'*")/I$42 -> 0.12162162
B46: excel | C46: =COUNTIFS('Jan - Copy & Paste'!$A$2:$A$3103,C$41,'Jan - Copy & Paste'!$P$2:$P$3103,"*'"&$B46&"'*")/C$42 -> 0.41446029 | D46: =COUNTIFS('Jan - Copy & Paste'!$A$2:$A$3103,D$41,'Jan - Copy & Paste'!$P$2:$P$3103,"*'"&$B46&"'*")/D$42 -> 0.10701956 | E46: =COUNTIFS('Jan - Copy & Paste'!$A$2:$A$3103,E$41,'Jan - Copy & Paste'!$P$2:$P$3103,"*'"&$B46&"'*")/E$42 -> 0.042145594 | F46: =COUNTIFS('Jan - Copy & Paste'!$A$2:$A$3103,F$41,'Jan - Copy & Paste'!$P$2:$P$3103,"*'"&$B46&"'*")/F$42 -> 0.39267016 | G46: =COUNTIFS('Jan - Copy & Paste'!$A$2:$A$3103,G$41,'Jan - Copy & Paste'!$P$2:$P$3103,"*'"&$B46&"'*")/G$42 -> 0.093220339 | H46: =COUNTIFS('Jan - Copy & Paste'!$A$2:$A$3103,H$41,'Jan - Copy & Paste'!$P$2:$P$3103,"*'"&$B46&"'*")/H$42 -> 0.020689655 | I46: =COUNTIFS('Jan - Copy & Paste'!$A$2:$A$3103,I$41,'Jan - Copy & Paste'!$P$2:$P$3103,"*'"&$B46&"'*")/I$42 -> 0.013513514
B47: tableau | C47: =COUNTIFS('Jan - Copy & Paste'!$A$2:$A$3103,C$41,'Jan - Copy & Paste'!$P$2:$P$3103,"*'"&$B47&"'*")/C$42 -> 0.26782077 | D47: =COUNTIFS('Jan - Copy & Paste'!$A$2:$A$3103,D$41,'Jan - Copy & Paste'!$P$2:$P$3103,"*'"&$B47&"'*")/D$42 -> 0.18757192 | E47: =COUNTIFS('Jan - Copy & Paste'!$A$2:$A$3103,E$41,'Jan - Copy & Paste'!$P$2:$P$3103,"*'"&$B47&"'*")/E$42 -> 0.11494253 | F47: =COUNTIFS('Jan - Copy & Paste'!$A$2:$A$3103,F$41,'Jan - Copy & Paste'!$P$2:$P$3103,"*'"&$B47&"'*")/F$42 -> 0.46073298 | G47: =COUNTIFS('Jan - Copy & Paste'!$A$2:$A$3103,G$41,'Jan - Copy & Paste'!$P$2:$P$3103,"*'"&$B47&"'*")/G$42 -> 0.18220339 | H47: =COUNTIFS('Jan - Copy & Paste'!$A$2:$A$3103,H$41,'Jan - Copy & Paste'!$P$2:$P$3103,"*'"&$B47&"'*")/H$42 -> 0.068965517 | I47: =COUNTIFS('Jan - Copy & Paste'!$A$2:$A$3103,I$41,'Jan - Copy & Paste'!$P$2:$P$3103,"*'"&$B47&"'*")/I$42 -> 0.027027027
B48: power bi | C48: =COUNTIFS('Jan - Copy & Paste'!$A$2:$A$3103,C$41,'Jan - Copy & Paste'!$P$2:$P$3103,"*'"&$B48&"'*")/C$42 -> 0.14663951 | D48: =COUNTIFS('Jan - Copy & Paste'!$A$2:$A$3103,D$41,'Jan - Copy & Paste'!$P$2:$P$3103,"*'"&$B48&"'*")/D$42 -> 0.065592635 | E48: =COUNTIFS('Jan - Copy & Paste'!$A$2:$A$3103,E$41,'Jan - Copy & Paste'!$P$2:$P$3103,"*'"&$B48&"'*")/E$42 -> 0.082375479 | F48: =COUNTIFS('Jan - Copy & Paste'!$A$2:$A$3103,F$41,'Jan - Copy & Paste'!$P$2:$P$3103,"*'"&$B48&"'*")/F$42 -> 0.2565445 | G48: =COUNTIFS('Jan - Copy & Paste'!$A$2:$A$3103,G$41,'Jan - Copy & Paste'!$P$2:$P$3103,"*'"&$B48&"'*")/G$42 -> 0.050847458 | H48: =COUNTIFS('Jan - Copy & Paste'!$A$2:$A$3103,H$41,'Jan - Copy & Paste'!$P$2:$P$3103,"*'"&$B48&"'*")/H$42 -> 0.04137931 | I48: =COUNTIFS('Jan - Copy & Paste'!$A$2:$A$3103,I$41,'Jan - Copy & Paste'!$P$2:$P$3103,"*'"&$B48&"'*")/I$42 -> 0
B49: aws | C49: =COUNTIFS('Jan - Copy & Paste'!$A$2:$A$3103,C$41,'Jan - Copy & Paste'!$P$2:$P$3103,"*'"&$B49&"'*")/C$42 -> 0.040733198 | D49: =COUNTIFS('Jan - Copy & Paste'!$A$2:$A$3103,D$41,'Jan - Copy & Paste'!$P$2:$P$3103,"*'"&$B49&"'*")/D$42 -> 0.20598389 | E49: =COUNTIFS('Jan - Copy & Paste'!$A$2:$A$3103,E$41,'Jan - Copy & Paste'!$P$2:$P$3103,"*'"&$B49&"'*")/E$42 -> 0.38122605 | F49: =COUNTIFS('Jan - Copy & Paste'!$A$2:$A$3103,F$41,'Jan - Copy & Paste'!$P$2:$P$3103,"*'"&$B49&"'*")/F$42 -> 0.057591623 | G49: =COUNTIFS('Jan - Copy & Paste'!$A$2:$A$3103,G$41,'Jan - Copy & Paste'!$P$2:$P$3103,"*'"&$B49&"'*")/G$42 -> 0.23728814 | H49: =COUNTIFS('Jan - Copy & Paste'!$A$2:$A$3103,H$41,'Jan - Copy & Paste'!$P$2:$P$3103,"*'"&$B49&"'*")/H$42 -> 0.57241379 | I49: =COUNTIFS('Jan - Copy & Paste'!$A$2:$A$3103,I$41,'Jan - Copy & Paste'!$P$2:$P$3103,"*'"&$B49&"'*")/I$42 -> 0.22972973
B50: azure | C50: =COUNTIFS('Jan - Copy & Paste'!$A$2:$A$3103,C$41,'Jan - Copy & Paste'!$P$2:$P$3103,"*'"&$B50&"'*")/C$42 -> 0.040733198 | D50: =COUNTIFS('Jan - Copy & Paste'!$A$2:$A$3103,D$41,'Jan - Copy & Paste'!$P$2:$P$3103,"*'"&$B50&"'*")/D$42 -> 0.10586881 | E50: =COUNTIFS('Jan - Copy & Paste'!$A$2:$A$3103,E$41,'Jan - Copy & Paste'!$P$2:$P$3103,"*'"&$B50&"'*")/E$42 -> 0.30842912 | F50: =COUNTIFS('Jan - Copy & Paste'!$A$2:$A$3103,F$41,'Jan - Copy & Paste'!$P$2:$P$3103,"*'"&$B50&"'*")/F$42 -> 0.031413613 | G50: =COUNTIFS('Jan - Copy & Paste'!$A$2:$A$3103,G$41,'Jan - Copy & Paste'!$P$2:$P$3103,"*'"&$B50&"'*")/G$42 -> 0.14830508 | H50: =COUNTIFS('Jan - Copy & Paste'!$A$2:$A$3103,H$41,'Jan - Copy & Paste'!$P$2:$P$3103,"*'"&$B50&"'*")/H$42 -> 0.40689655 | I50: =COUNTIFS('Jan - Copy & Paste'!$A$2:$A$3103,I$41,'Jan - Copy & Paste'!$P$2:$P$3103,"*'"&$B50&"'*")/I$42 -> 0.16216216
B51: spark | C51: =COUNTIFS('Jan - Copy & Paste'!$A$2:$A$3103,C$41,'Jan - Copy & Paste'!$P$2:$P$3103,"*'"&$B51&"'*")/C$42 -> 0.025458248 | D51: =COUNTIFS('Jan - Copy & Paste'!$A$2:$A$3103,D$41,'Jan - Copy & Paste'!$P$2:$P$3103,"*'"&$B51&"'*")/D$42 -> 0.16570771 | E51: =COUNTIFS('Jan - Copy & Paste'!$A$2:$A$3103,E$41,'Jan - Copy & Paste'!$P$2:$P$3103,"*'"&$B51&"'*")/E$42 -> 0.33333333 | F51: =COUNTIFS('Jan - Copy & Paste'!$A$2:$A$3103,F$41,'Jan - Copy & Paste'!$P$2:$P$3103,"*'"&$B51&"'*")/F$42 -> 0.041884817 | G51: =COUNTIFS('Jan - Copy & Paste'!$A$2:$A$3103,G$41,'Jan - Copy & Paste'!$P$2:$P$3103,"*'"&$B51&"'*")/G$42 -> 0.22881356 | H51: =COUNTIFS('Jan - Copy & Paste'!$A$2:$A$3103,H$41,'Jan - Copy & Paste'!$P$2:$P$3103,"*'"&$B51&"'*")/H$42 -> 0.46896552 | I51: =COUNTIFS('Jan - Copy & Paste'!$A$2:$A$3103,I$41,'Jan - Copy & Paste'!$P$2:$P$3103,"*'"&$B51&"'*")/I$42 -> 0.16216216
B52: sas | C52: =COUNTIFS('Jan - Copy & Paste'!$A$2:$A$3103,C$41,'Jan - Copy & Paste'!$P$2:$P$3103,"*'"&$B52&"'*")/C$42 -> 0.080448065 | D52: =COUNTIFS('Jan - Copy & Paste'!$A$2:$A$3103,D$41,'Jan - Copy & Paste'!$P$2:$P$3103,"*'"&$B52&"'*")/D$42 -> 0.084004603 | E52: =COUNTIFS('Jan - Copy & Paste'!$A$2:$A$3103,E$41,'Jan - Copy & Paste'!$P$2:$P$3103,"*'"&$B52&"'*")/E$42 -> 0.013409962 | F52: =COUNTIFS('Jan - Copy & Paste'!$A$2:$A$3103,F$41,'Jan - Copy & Paste'!$P$2:$P$3103,"*'"&$B52&"'*")/F$42 -> 0.10994764 | G52: =COUNTIFS('Jan - Copy & Paste'!$A$2:$A$3103,G$41,'Jan - Copy & Paste'!$P$2:$P$3103,"*'"&$B52&"'*")/G$42 -> 0.084745763 | H52: =COUNTIFS('Jan - Copy & Paste'!$A$2:$A$3103,H$41,'Jan - Copy & Paste'!$P$2:$P$3103,"*'"&$B52&"'*")/H$42 -> 0.034482759 | I52: =COUNTIFS('Jan - Copy & Paste'!$A$2:$A$3103,I$41,'Jan - Copy & Paste'!$P$2:$P$3103,"*'"&$B52&"'*")/I$42 -> 0
B53: tensorflow | C53: =COUNTIFS('Jan - Copy & Paste'!$A$2:$A$3103,C$41,'Jan - Copy & Paste'!$P$2:$P$3103,"*'"&$B53&"'*")/C$42 -> 0.0030549898 | D53: =COUNTIFS('Jan - Copy & Paste'!$A$2:$A$3103,D$41,'Jan - Copy & Paste'!$P$2:$P$3103,"*'"&$B53&"'*")/D$42 -> 0.10932106 | E53: =COUNTIFS('Jan - Copy & Paste'!$A$2:$A$3103,E$41,'Jan - Copy & Paste'!$P$2:$P$3103,"*'"&$B53&"'*")/E$42 -> 0.0095785441 | F53: =COUNTIFS('Jan - Copy & Paste'!$A$2:$A$3103,F$41,'Jan - Copy & Paste'!$P$2:$P$3103,"*'"&$B53&"'*")/F$42 -> 0.010471204 | G53: =COUNTIFS('Jan - Copy & Paste'!$A$2:$A$3103,G$41,'Jan - Copy & Paste'!$P$2:$P$3103,"*'"&$B53&"'*")/G$42 -> 0.10169492 | H53: =COUNTIFS('Jan - Copy & Paste'!$A$2:$A$3103,H$41,'Jan - Copy & Paste'!$P$2:$P$3103,"*'"&$B53&"'*")/H$42 -> 0.0068965517 | I53: =COUNTIFS('Jan - Copy & Paste'!$A$2:$A$3103,I$41,'Jan - Copy & Paste'!$P$2:$P$3103,"*'"&$B53&"'*")/I$42 -> 0.33783784
B54: pytorch | C54: =COUNTIFS('Jan - Copy & Paste'!$A$2:$A$3103,C$41,'Jan - Copy & Paste'!$P$2:$P$3103,"*'"&$B54&"'*")/C$42 -> 0.0020366599 | D54: =COUNTIFS('Jan - Copy & Paste'!$A$2:$A$3103,D$41,'Jan - Copy & Paste'!$P$2:$P$3103,"*'"&$B54&"'*")/D$42 -> 0.093210587 | E54: =COUNTIFS('Jan - Copy & Paste'!$A$2:$A$3103,E$41,'Jan - Copy & Paste'!$P$2:$P$3103,"*'"&$B54&"'*")/E$42 -> 0.0076628352 | F54: =COUNTIFS('Jan - Copy & Paste'!$A$2:$A$3103,F$41,'Jan - Copy & Paste'!$P$2:$P$3103,"*'"&$B54&"'*")/F$42 -> 0.0052356021 | G54: =COUNTIFS('Jan - Copy & Paste'!$A$2:$A$3103,G$41,'Jan - Copy & Paste'!$P$2:$P$3103,"*'"&$B54&"'*")/G$42 -> 0.072033898 | H54: =COUNTIFS('Jan - Copy & Paste'!$A$2:$A$3103,H$41,'Jan - Copy & Paste'!$P$2:$P$3103,"*'"&$B54&"'*")/H$42 -> 0 | I54: =COUNTIFS('Jan - Copy & Paste'!$A$2:$A$3103,I$41,'Jan - Copy & Paste'!$P$2:$P$3103,"*'"&$B54&"'*")/I$42 -> 0.31081081
A56: Key takeaways
A57: 1. SQL and Python are the baseline: they appear in ~64% and ~59% of all postings that list skills. No other skill clears 26%.
A58: 2. Demand and pay diverge. The highest-paying skills are data-engineering tooling — Scala, Redshift, Kafka, Airflow, Spark, Hadoop (all +15% to +20% vs the $123k overall average) — despite appearing in under 18% of postings.
A59: 3. Office/BI tools carry a discount: PowerPoint (-22%), Word (-20%), Excel (-19%), Power BI (-15%). They cluster in Data Analyst roles, where Excel appears in 41% of postings.
A60: 4. Skill mix is role-specific: Excel/Tableau/Power BI for analysts, AWS/Azure/Spark for engineers (Spark in 47% of Senior Data Engineer postings), TensorFlow/PyTorch almost exclusively for ML Engineers (34%/31%).
A61: 5. Caveat: salary averages use only the 2,287 postings with an annual figure; the 'n' column shows the sample behind each skill.
